# 2015.01.14 22:42:50 CET
--- This code section failed: ---
0	LOAD_CONST        -1
3	LOAD_CONST        ''
6	IMPORT_NAME       'time'
9	STORE_NAME        'time'
12	LOAD_CONST        -1
15	LOAD_CONST        ''
18	IMPORT_NAME       'constants'
21	STORE_NAME        'constants'
24	LOAD_CONST        -1
27	LOAD_CONST        ''
30	IMPORT_NAME       'zlib'
33	STORE_NAME        'zlib'
36	LOAD_CONST        -1
39	LOAD_CONST        ''
42	IMPORT_NAME       'cPickle'
45	STORE_NAME        'cPickle'
48	LOAD_CONST        -1
51	LOAD_CONST        ('Event',)
54	IMPORT_NAME       'Event'
57	IMPORT_FROM       'Event'
60	STORE_NAME        'Event'
63	POP_TOP           ''
64	LOAD_CONST        -1
67	LOAD_CONST        ('wraps',)
70	IMPORT_NAME       'functools'
73	IMPORT_FROM       'wraps'
76	STORE_NAME        'wraps'
79	POP_TOP           ''
80	LOAD_CONST        -1
83	LOAD_CONST        ('noexcept',)
86	IMPORT_NAME       'wotdecorators'
89	IMPORT_FROM       'noexcept'
92	STORE_NAME        'noexcept'
95	POP_TOP           ''
96	LOAD_CONST        -1
99	LOAD_CONST        ('LOG_RF', 'LOG_ERROR')
102	IMPORT_NAME       'debug_utils'
105	IMPORT_FROM       'LOG_RF'
108	STORE_NAME        'LOG_RF'
111	IMPORT_FROM       'LOG_ERROR'
114	STORE_NAME        'LOG_ERROR'
117	POP_TOP           ''
118	LOAD_CONST        -1
121	LOAD_CONST        ('CHAT_LOG', 'RESTRICTION_TYPE')
124	IMPORT_NAME       'constants'
127	IMPORT_FROM       'CHAT_LOG'
130	STORE_NAME        'CHAT_LOG'
133	IMPORT_FROM       'RESTRICTION_TYPE'
136	STORE_NAME        'RESTRICTION_TYPE'
139	POP_TOP           ''
140	LOAD_CONST        -1
143	LOAD_CONST        ('Enumeration', 'AttributeEnumItem')
146	IMPORT_NAME       'enumerations'
149	IMPORT_FROM       'Enumeration'
152	STORE_NAME        'Enumeration'
155	IMPORT_FROM       'AttributeEnumItem'
158	STORE_NAME        'AttributeEnumItem'
161	POP_TOP           ''
162	LOAD_CONST        'CHAT_ACTIONS'
165	LOAD_CONST        'CHAT_ACTION_RESPONSES'
168	BUILD_LIST_2      ''
171	STORE_NAME        '__all__'
174	LOAD_NAME         'Enumeration'
177	LOAD_CONST        'Group of members for notification'
180	LOAD_CONST        'All'
183	LOAD_CONST        'None'
186	LOAD_CONST        'Originator'
189	LOAD_CONST        'ExceptOriginator'
192	BUILD_LIST_4      ''
195	CALL_FUNCTION_2   ''
198	STORE_NAME        'NOTIFICATION_GROUP'
201	LOAD_CONST        '<code_object __notifyFilterAll>'
204	MAKE_FUNCTION_0   ''
207	STORE_NAME        '__notifyFilterAll'
210	LOAD_CONST        '<code_object __notifyFilterNone>'
213	MAKE_FUNCTION_0   ''
216	STORE_NAME        '__notifyFilterNone'
219	LOAD_CONST        '<code_object __notifyFilterOnlyOriginator>'
222	MAKE_FUNCTION_0   ''
225	STORE_NAME        '__notifyFilterOnlyOriginator'
228	LOAD_CONST        '<code_object __notifyFilterExceptOriginator>'
231	MAKE_FUNCTION_0   ''
234	STORE_NAME        '__notifyFilterExceptOriginator'
237	LOAD_NAME         'constants'
240	LOAD_ATTR         'IS_BASEAPP'
243	POP_JUMP_IF_FALSE '1530'
246	LOAD_NAME         'Enumeration'
249	LOAD_CONST        'chatChannelActions'
252	LOAD_CONST        'enter'
255	BUILD_MAP         ''
258	LOAD_NAME         '__notifyFilterExceptOriginator'
261	LOAD_CONST        'notifyFilter'
264	STORE_MAP         ''
265	LOAD_NAME         'NOTIFICATION_GROUP'
268	LOAD_ATTR         'ExceptOriginator'
271	LOAD_CONST        'notificationGroup'
274	STORE_MAP         ''
275	LOAD_NAME         'CHAT_LOG'
278	LOAD_ATTR         'ACTIONS'
281	LOAD_CONST        'logLevel'
284	STORE_MAP         ''
285	BUILD_TUPLE_2     ''
288	LOAD_CONST        'broadcast'
291	BUILD_MAP         ''
294	LOAD_NAME         '__notifyFilterAll'
297	LOAD_CONST        'notifyFilter'
300	STORE_MAP         ''
301	LOAD_NAME         'NOTIFICATION_GROUP'
304	LOAD_ATTR         'All'
307	LOAD_CONST        'notificationGroup'
310	STORE_MAP         ''
311	LOAD_NAME         'CHAT_LOG'
314	LOAD_ATTR         'MESSAGES'
317	LOAD_CONST        'logLevel'
320	STORE_MAP         ''
321	BUILD_TUPLE_2     ''
324	LOAD_CONST        'leave'
327	BUILD_MAP         ''
330	LOAD_NAME         '__notifyFilterExceptOriginator'
333	LOAD_CONST        'notifyFilter'
336	STORE_MAP         ''
337	LOAD_NAME         'NOTIFICATION_GROUP'
340	LOAD_ATTR         'ExceptOriginator'
343	LOAD_CONST        'notificationGroup'
346	STORE_MAP         ''
347	LOAD_NAME         'CHAT_LOG'
350	LOAD_ATTR         'ACTIONS'
353	LOAD_CONST        'logLevel'
356	STORE_MAP         ''
357	BUILD_TUPLE_2     ''
360	LOAD_CONST        'requestMembers'
363	BUILD_MAP         ''
366	LOAD_NAME         '__notifyFilterOnlyOriginator'
369	LOAD_CONST        'notifyFilter'
372	STORE_MAP         ''
373	LOAD_NAME         'NOTIFICATION_GROUP'
376	LOAD_ATTR         'Originator'
379	LOAD_CONST        'notificationGroup'
382	STORE_MAP         ''
383	LOAD_NAME         'CHAT_LOG'
386	LOAD_ATTR         'NONE'
389	LOAD_CONST        'logLevel'
392	STORE_MAP         ''
393	BUILD_TUPLE_2     ''
396	LOAD_CONST        'channelDestroyed'
399	BUILD_MAP         ''
402	LOAD_NAME         '__notifyFilterAll'
405	LOAD_CONST        'notifyFilter'
408	STORE_MAP         ''
409	LOAD_NAME         'NOTIFICATION_GROUP'
412	LOAD_ATTR         'All'
415	LOAD_CONST        'notificationGroup'
418	STORE_MAP         ''
419	LOAD_NAME         'CHAT_LOG'
422	LOAD_ATTR         'ACTIONS'
425	LOAD_CONST        'logLevel'
428	STORE_MAP         ''
429	BUILD_TUPLE_2     ''
432	LOAD_CONST        'createChannel'
435	BUILD_MAP         ''
438	LOAD_NAME         '__notifyFilterOnlyOriginator'
441	LOAD_CONST        'notifyFilter'
444	STORE_MAP         ''
445	LOAD_NAME         'NOTIFICATION_GROUP'
448	LOAD_ATTR         'Originator'
451	LOAD_CONST        'notificationGroup'
454	STORE_MAP         ''
455	LOAD_NAME         'CHAT_LOG'
458	LOAD_ATTR         'ACTIONS'
461	LOAD_CONST        'logLevel'
464	STORE_MAP         ''
465	BUILD_TUPLE_2     ''
468	LOAD_CONST        'requestChannels'
471	BUILD_MAP         ''
474	LOAD_NAME         '__notifyFilterOnlyOriginator'
477	LOAD_CONST        'notifyFilter'
480	STORE_MAP         ''
481	LOAD_NAME         'NOTIFICATION_GROUP'
484	LOAD_ATTR         'Originator'
487	LOAD_CONST        'notificationGroup'
490	STORE_MAP         ''
491	LOAD_NAME         'CHAT_LOG'
494	LOAD_ATTR         'NONE'
497	LOAD_CONST        'logLevel'
500	STORE_MAP         ''
501	BUILD_TUPLE_2     ''
504	LOAD_CONST        'selfEnter'
507	BUILD_MAP         ''
510	LOAD_NAME         '__notifyFilterOnlyOriginator'
513	LOAD_CONST        'notifyFilter'
516	STORE_MAP         ''
517	LOAD_NAME         'NOTIFICATION_GROUP'
520	LOAD_ATTR         'Originator'
523	LOAD_CONST        'notificationGroup'
526	STORE_MAP         ''
527	LOAD_NAME         'CHAT_LOG'
530	LOAD_ATTR         'NONE'
533	LOAD_CONST        'logLevel'
536	STORE_MAP         ''
537	BUILD_TUPLE_2     ''
540	LOAD_CONST        'selfLeave'
543	BUILD_MAP         ''
546	LOAD_NAME         '__notifyFilterOnlyOriginator'
549	LOAD_CONST        'notifyFilter'
552	STORE_MAP         ''
553	LOAD_NAME         'NOTIFICATION_GROUP'
556	LOAD_ATTR         'Originator'
559	LOAD_CONST        'notificationGroup'
562	STORE_MAP         ''
563	LOAD_NAME         'CHAT_LOG'
566	LOAD_ATTR         'NONE'
569	LOAD_CONST        'logLevel'
572	STORE_MAP         ''
573	BUILD_TUPLE_2     ''
576	LOAD_CONST        'requestMessageHistory'
579	BUILD_MAP         ''
582	LOAD_NAME         '__notifyFilterOnlyOriginator'
585	LOAD_CONST        'notifyFilter'
588	STORE_MAP         ''
589	LOAD_NAME         'NOTIFICATION_GROUP'
592	LOAD_ATTR         'Originator'
595	LOAD_CONST        'notificationGroup'
598	STORE_MAP         ''
599	LOAD_NAME         'CHAT_LOG'
602	LOAD_ATTR         'NONE'
605	LOAD_CONST        'logLevel'
608	STORE_MAP         ''
609	BUILD_TUPLE_2     ''
612	LOAD_CONST        'channelInfoUpdated'
615	BUILD_MAP         ''
618	LOAD_NAME         '__notifyFilterAll'
621	LOAD_CONST        'notifyFilter'
624	STORE_MAP         ''
625	LOAD_NAME         'NOTIFICATION_GROUP'
628	LOAD_ATTR         'All'
631	LOAD_CONST        'notificationGroup'
634	STORE_MAP         ''
635	LOAD_NAME         'CHAT_LOG'
638	LOAD_ATTR         'NONE'
641	LOAD_CONST        'logLevel'
644	STORE_MAP         ''
645	BUILD_TUPLE_2     ''
648	LOAD_CONST        'memberStatusUpdate'
651	BUILD_MAP         ''
654	LOAD_NAME         '__notifyFilterAll'
657	LOAD_CONST        'notifyFilter'
660	STORE_MAP         ''
661	LOAD_NAME         'NOTIFICATION_GROUP'
664	LOAD_ATTR         'All'
667	LOAD_CONST        'notificationGroup'
670	STORE_MAP         ''
671	LOAD_NAME         'CHAT_LOG'
674	LOAD_ATTR         'NONE'
677	LOAD_CONST        'logLevel'
680	STORE_MAP         ''
681	BUILD_TUPLE_2     ''
684	LOAD_CONST        'findUsers'
687	BUILD_MAP         ''
690	LOAD_NAME         '__notifyFilterOnlyOriginator'
693	LOAD_CONST        'notifyFilter'
696	STORE_MAP         ''
697	LOAD_NAME         'NOTIFICATION_GROUP'
700	LOAD_ATTR         'Originator'
703	LOAD_CONST        'notificationGroup'
706	STORE_MAP         ''
707	LOAD_NAME         'CHAT_LOG'
710	LOAD_ATTR         'NONE'
713	LOAD_CONST        'logLevel'
716	STORE_MAP         ''
717	BUILD_TUPLE_2     ''
720	LOAD_CONST        'requestUsersRoster'
723	BUILD_MAP         ''
726	LOAD_NAME         '__notifyFilterOnlyOriginator'
729	LOAD_CONST        'notifyFilter'
732	STORE_MAP         ''
733	LOAD_NAME         'NOTIFICATION_GROUP'
736	LOAD_ATTR         'Originator'
739	LOAD_CONST        'notificationGroup'
742	STORE_MAP         ''
743	LOAD_NAME         'CHAT_LOG'
746	LOAD_ATTR         'NONE'
749	LOAD_CONST        'logLevel'
752	STORE_MAP         ''
753	BUILD_TUPLE_2     ''
756	LOAD_CONST        'addIgnored'
759	BUILD_MAP         ''
762	LOAD_NAME         '__notifyFilterOnlyOriginator'
765	LOAD_CONST        'notifyFilter'
768	STORE_MAP         ''
769	LOAD_NAME         'NOTIFICATION_GROUP'
772	LOAD_ATTR         'Originator'
775	LOAD_CONST        'notificationGroup'
778	STORE_MAP         ''
779	LOAD_NAME         'CHAT_LOG'
782	LOAD_ATTR         'NONE'
785	LOAD_CONST        'logLevel'
788	STORE_MAP         ''
789	BUILD_TUPLE_2     ''
792	LOAD_CONST        'addFriend'
795	BUILD_MAP         ''
798	LOAD_NAME         '__notifyFilterOnlyOriginator'
801	LOAD_CONST        'notifyFilter'
804	STORE_MAP         ''
805	LOAD_NAME         'NOTIFICATION_GROUP'
808	LOAD_ATTR         'Originator'
811	LOAD_CONST        'notificationGroup'
814	STORE_MAP         ''
815	LOAD_NAME         'CHAT_LOG'
818	LOAD_ATTR         'NONE'
821	LOAD_CONST        'logLevel'
824	STORE_MAP         ''
825	BUILD_TUPLE_2     ''
828	LOAD_CONST        'removeIgnored'
831	BUILD_MAP         ''
834	LOAD_NAME         '__notifyFilterOnlyOriginator'
837	LOAD_CONST        'notifyFilter'
840	STORE_MAP         ''
841	LOAD_NAME         'NOTIFICATION_GROUP'
844	LOAD_ATTR         'Originator'
847	LOAD_CONST        'notificationGroup'
850	STORE_MAP         ''
851	LOAD_NAME         'CHAT_LOG'
854	LOAD_ATTR         'NONE'
857	LOAD_CONST        'logLevel'
860	STORE_MAP         ''
861	BUILD_TUPLE_2     ''
864	LOAD_CONST        'removeFriend'
867	BUILD_MAP         ''
870	LOAD_NAME         '__notifyFilterOnlyOriginator'
873	LOAD_CONST        'notifyFilter'
876	STORE_MAP         ''
877	LOAD_NAME         'NOTIFICATION_GROUP'
880	LOAD_ATTR         'Originator'
883	LOAD_CONST        'notificationGroup'
886	STORE_MAP         ''
887	LOAD_NAME         'CHAT_LOG'
890	LOAD_ATTR         'NONE'
893	LOAD_CONST        'logLevel'
896	STORE_MAP         ''
897	BUILD_TUPLE_2     ''
900	LOAD_CONST        'createPrivate'
903	BUILD_MAP         ''
906	LOAD_NAME         '__notifyFilterOnlyOriginator'
909	LOAD_CONST        'notifyFilter'
912	STORE_MAP         ''
913	LOAD_NAME         'NOTIFICATION_GROUP'
916	LOAD_ATTR         'Originator'
919	LOAD_CONST        'notificationGroup'
922	STORE_MAP         ''
923	LOAD_NAME         'CHAT_LOG'
926	LOAD_ATTR         'NONE'
929	LOAD_CONST        'logLevel'
932	STORE_MAP         ''
933	BUILD_TUPLE_2     ''
936	LOAD_CONST        'friendStatusUpdate'
939	BUILD_MAP         ''
942	LOAD_NAME         '__notifyFilterOnlyOriginator'
945	LOAD_CONST        'notifyFilter'
948	STORE_MAP         ''
949	LOAD_NAME         'NOTIFICATION_GROUP'
952	LOAD_ATTR         'Originator'
955	LOAD_CONST        'notificationGroup'
958	STORE_MAP         ''
959	LOAD_NAME         'CHAT_LOG'
962	LOAD_ATTR         'NONE'
965	LOAD_CONST        'logLevel'
968	STORE_MAP         ''
969	BUILD_TUPLE_2     ''
972	LOAD_CONST        'userChatCommand'
975	BUILD_MAP         ''
978	LOAD_NAME         '__notifyFilterAll'
981	LOAD_CONST        'notifyFilter'
984	STORE_MAP         ''
985	LOAD_NAME         'NOTIFICATION_GROUP'
988	LOAD_ATTR         'All'
991	LOAD_CONST        'notificationGroup'
994	STORE_MAP         ''
995	LOAD_NAME         'CHAT_LOG'
998	LOAD_ATTR         'ACTIONS'
1001	LOAD_CONST        'logLevel'
1004	STORE_MAP         ''
1005	BUILD_TUPLE_2     ''
1008	LOAD_CONST        'sysMessage'
1011	BUILD_MAP         ''
1014	LOAD_NAME         '__notifyFilterAll'
1017	LOAD_CONST        'notifyFilter'
1020	STORE_MAP         ''
1021	LOAD_NAME         'NOTIFICATION_GROUP'
1024	LOAD_ATTR         'All'
1027	LOAD_CONST        'notificationGroup'
1030	STORE_MAP         ''
1031	LOAD_NAME         'CHAT_LOG'
1034	LOAD_ATTR         'NONE'
1037	LOAD_CONST        'logLevel'
1040	STORE_MAP         ''
1041	BUILD_TUPLE_2     ''
1044	LOAD_CONST        'personalSysMessage'
1047	BUILD_MAP         ''
1050	LOAD_NAME         '__notifyFilterAll'
1053	LOAD_CONST        'notifyFilter'
1056	STORE_MAP         ''
1057	LOAD_NAME         'NOTIFICATION_GROUP'
1060	LOAD_ATTR         'All'
1063	LOAD_CONST        'notificationGroup'
1066	STORE_MAP         ''
1067	LOAD_NAME         'CHAT_LOG'
1070	LOAD_ATTR         'NONE'
1073	LOAD_CONST        'logLevel'
1076	STORE_MAP         ''
1077	BUILD_TUPLE_2     ''
1080	LOAD_CONST        'chatInitialization'
1083	BUILD_MAP         ''
1086	LOAD_NAME         '__notifyFilterAll'
1089	LOAD_CONST        'notifyFilter'
1092	STORE_MAP         ''
1093	LOAD_NAME         'NOTIFICATION_GROUP'
1096	LOAD_ATTR         'All'
1099	LOAD_CONST        'notificationGroup'
1102	STORE_MAP         ''
1103	LOAD_NAME         'CHAT_LOG'
1106	LOAD_ATTR         'ACTIONS'
1109	LOAD_CONST        'logLevel'
1112	STORE_MAP         ''
1113	BUILD_TUPLE_2     ''
1116	LOAD_CONST        'userInviteCommand'
1119	BUILD_MAP         ''
1122	LOAD_NAME         '__notifyFilterAll'
1125	LOAD_CONST        'notifyFilter'
1128	STORE_MAP         ''
1129	LOAD_NAME         'NOTIFICATION_GROUP'
1132	LOAD_ATTR         'All'
1135	LOAD_CONST        'notificationGroup'
1138	STORE_MAP         ''
1139	LOAD_NAME         'CHAT_LOG'
1142	LOAD_ATTR         'ACTIONS'
1145	LOAD_CONST        'logLevel'
1148	STORE_MAP         ''
1149	BUILD_TUPLE_2     ''
1152	LOAD_CONST        'createInvite'
1155	BUILD_MAP         ''
1158	LOAD_NAME         '__notifyFilterOnlyOriginator'
1161	LOAD_CONST        'notifyFilter'
1164	STORE_MAP         ''
1165	LOAD_NAME         'NOTIFICATION_GROUP'
1168	LOAD_ATTR         'Originator'
1171	LOAD_CONST        'notificationGroup'
1174	STORE_MAP         ''
1175	LOAD_NAME         'CHAT_LOG'
1178	LOAD_ATTR         'ACTIONS'
1181	LOAD_CONST        'logLevel'
1184	STORE_MAP         ''
1185	BUILD_TUPLE_2     ''
1188	LOAD_CONST        'receiveInvite'
1191	BUILD_MAP         ''
1194	LOAD_NAME         '__notifyFilterOnlyOriginator'
1197	LOAD_CONST        'notifyFilter'
1200	STORE_MAP         ''
1201	LOAD_NAME         'NOTIFICATION_GROUP'
1204	LOAD_ATTR         'Originator'
1207	LOAD_CONST        'notificationGroup'
1210	STORE_MAP         ''
1211	LOAD_NAME         'CHAT_LOG'
1214	LOAD_ATTR         'ACTIONS'
1217	LOAD_CONST        'logLevel'
1220	STORE_MAP         ''
1221	BUILD_TUPLE_2     ''
1224	LOAD_CONST        'receiveArchiveInvite'
1227	BUILD_MAP         ''
1230	LOAD_NAME         '__notifyFilterOnlyOriginator'
1233	LOAD_CONST        'notifyFilter'
1236	STORE_MAP         ''
1237	LOAD_NAME         'NOTIFICATION_GROUP'
1240	LOAD_ATTR         'Originator'
1243	LOAD_CONST        'notificationGroup'
1246	STORE_MAP         ''
1247	LOAD_NAME         'CHAT_LOG'
1250	LOAD_ATTR         'ACTIONS'
1253	LOAD_CONST        'logLevel'
1256	STORE_MAP         ''
1257	BUILD_TUPLE_2     ''
1260	LOAD_CONST        'receiveMembersCount'
1263	BUILD_MAP         ''
1266	LOAD_NAME         '__notifyFilterOnlyOriginator'
1269	LOAD_CONST        'notifyFilter'
1272	STORE_MAP         ''
1273	LOAD_NAME         'NOTIFICATION_GROUP'
1276	LOAD_ATTR         'Originator'
1279	LOAD_CONST        'notificationGroup'
1282	STORE_MAP         ''
1283	LOAD_NAME         'CHAT_LOG'
1286	LOAD_ATTR         'ACTIONS'
1289	LOAD_CONST        'logLevel'
1292	STORE_MAP         ''
1293	BUILD_TUPLE_2     ''
1296	LOAD_CONST        'receiveMembersDelta'
1299	BUILD_MAP         ''
1302	LOAD_NAME         '__notifyFilterOnlyOriginator'
1305	LOAD_CONST        'notifyFilter'
1308	STORE_MAP         ''
1309	LOAD_NAME         'NOTIFICATION_GROUP'
1312	LOAD_ATTR         'All'
1315	LOAD_CONST        'notificationGroup'
1318	STORE_MAP         ''
1319	LOAD_NAME         'CHAT_LOG'
1322	LOAD_ATTR         'ACTIONS'
1325	LOAD_CONST        'logLevel'
1328	STORE_MAP         ''
1329	BUILD_TUPLE_2     ''
1332	LOAD_CONST        'VOIPSettings'
1335	BUILD_MAP         ''
1338	LOAD_NAME         '__notifyFilterAll'
1341	LOAD_CONST        'notifyFilter'
1344	STORE_MAP         ''
1345	LOAD_NAME         'NOTIFICATION_GROUP'
1348	LOAD_ATTR         'All'
1351	LOAD_CONST        'notificationGroup'
1354	STORE_MAP         ''
1355	LOAD_NAME         'CHAT_LOG'
1358	LOAD_ATTR         'ACTIONS'
1361	LOAD_CONST        'logLevel'
1364	STORE_MAP         ''
1365	BUILD_TUPLE_2     ''
1368	LOAD_CONST        'VOIPCredentials'
1371	BUILD_MAP         ''
1374	LOAD_NAME         '__notifyFilterAll'
1377	LOAD_CONST        'notifyFilter'
1380	STORE_MAP         ''
1381	LOAD_NAME         'NOTIFICATION_GROUP'
1384	LOAD_ATTR         'All'
1387	LOAD_CONST        'notificationGroup'
1390	STORE_MAP         ''
1391	LOAD_NAME         'CHAT_LOG'
1394	LOAD_ATTR         'ACTIONS'
1397	LOAD_CONST        'logLevel'
1400	STORE_MAP         ''
1401	BUILD_TUPLE_2     ''
1404	LOAD_CONST        'setMuted'
1407	BUILD_MAP         ''
1410	LOAD_NAME         '__notifyFilterOnlyOriginator'
1413	LOAD_CONST        'notifyFilter'
1416	STORE_MAP         ''
1417	LOAD_NAME         'NOTIFICATION_GROUP'
1420	LOAD_ATTR         'Originator'
1423	LOAD_CONST        'notificationGroup'
1426	STORE_MAP         ''
1427	LOAD_NAME         'CHAT_LOG'
1430	LOAD_ATTR         'NONE'
1433	LOAD_CONST        'logLevel'
1436	STORE_MAP         ''
1437	BUILD_TUPLE_2     ''
1440	LOAD_CONST        'unsetMuted'
1443	BUILD_MAP         ''
1446	LOAD_NAME         '__notifyFilterOnlyOriginator'
1449	LOAD_CONST        'notifyFilter'
1452	STORE_MAP         ''
1453	LOAD_NAME         'NOTIFICATION_GROUP'
1456	LOAD_ATTR         'Originator'
1459	LOAD_CONST        'notificationGroup'
1462	STORE_MAP         ''
1463	LOAD_NAME         'CHAT_LOG'
1466	LOAD_ATTR         'NONE'
1469	LOAD_CONST        'logLevel'
1472	STORE_MAP         ''
1473	BUILD_TUPLE_2     ''
1476	LOAD_CONST        'logVivoxLogin'
1479	BUILD_MAP         ''
1482	LOAD_NAME         '__notifyFilterNone'
1485	LOAD_CONST        'notifyFilter'
1488	STORE_MAP         ''
1489	LOAD_NAME         'NOTIFICATION_GROUP'
1492	LOAD_ATTR         'None'
1495	LOAD_CONST        'notificationGroup'
1498	STORE_MAP         ''
1499	LOAD_NAME         'CHAT_LOG'
1502	LOAD_ATTR         'NONE'
1505	LOAD_CONST        'logLevel'
1508	STORE_MAP         ''
1509	BUILD_TUPLE_2     ''
1512	BUILD_LIST_35     ''
1515	LOAD_CONST        'instance'
1518	LOAD_NAME         'AttributeEnumItem'
1521	CALL_FUNCTION_258 ''
1524	STORE_NAME        'CHAT_ACTIONS'
1527	JUMP_FORWARD      '1866'
1530	LOAD_NAME         'Enumeration'
1533	LOAD_CONST        'chatActions'
1536	LOAD_CONST        'enter'
1539	BUILD_MAP         ''
1542	BUILD_TUPLE_2     ''
1545	LOAD_CONST        'broadcast'
1548	BUILD_MAP         ''
1551	BUILD_TUPLE_2     ''
1554	LOAD_CONST        'leave'
1557	BUILD_MAP         ''
1560	BUILD_TUPLE_2     ''
1563	LOAD_CONST        'requestMembers'
1566	BUILD_MAP         ''
1569	BUILD_TUPLE_2     ''
1572	LOAD_CONST        'channelDestroyed'
1575	BUILD_MAP         ''
1578	BUILD_TUPLE_2     ''
1581	LOAD_CONST        'createChannel'
1584	BUILD_MAP         ''
1587	BUILD_TUPLE_2     ''
1590	LOAD_CONST        'requestChannels'
1593	BUILD_MAP         ''
1596	BUILD_TUPLE_2     ''
1599	LOAD_CONST        'selfEnter'
1602	BUILD_MAP         ''
1605	BUILD_TUPLE_2     ''
1608	LOAD_CONST        'selfLeave'
1611	BUILD_MAP         ''
1614	BUILD_TUPLE_2     ''
1617	LOAD_CONST        'requestMessageHistory'
1620	BUILD_MAP         ''
1623	BUILD_TUPLE_2     ''
1626	LOAD_CONST        'channelInfoUpdated'
1629	BUILD_MAP         ''
1632	BUILD_TUPLE_2     ''
1635	LOAD_CONST        'memberStatusUpdate'
1638	BUILD_MAP         ''
1641	BUILD_TUPLE_2     ''
1644	LOAD_CONST        'findUsers'
1647	BUILD_MAP         ''
1650	BUILD_TUPLE_2     ''
1653	LOAD_CONST        'requestUsersRoster'
1656	BUILD_MAP         ''
1659	BUILD_TUPLE_2     ''
1662	LOAD_CONST        'addIgnored'
1665	BUILD_MAP         ''
1668	BUILD_TUPLE_2     ''
1671	LOAD_CONST        'addFriend'
1674	BUILD_MAP         ''
1677	BUILD_TUPLE_2     ''
1680	LOAD_CONST        'removeIgnored'
1683	BUILD_MAP         ''
1686	BUILD_TUPLE_2     ''
1689	LOAD_CONST        'removeFriend'
1692	BUILD_MAP         ''
1695	BUILD_TUPLE_2     ''
1698	LOAD_CONST        'createPrivate'
1701	BUILD_MAP         ''
1704	BUILD_TUPLE_2     ''
1707	LOAD_CONST        'friendStatusUpdate'
1710	BUILD_MAP         ''
1713	BUILD_TUPLE_2     ''
1716	LOAD_CONST        'userChatCommand'
1719	BUILD_MAP         ''
1722	BUILD_TUPLE_2     ''
1725	LOAD_CONST        'sysMessage'
1728	BUILD_MAP         ''
1731	BUILD_TUPLE_2     ''
1734	LOAD_CONST        'personalSysMessage'
1737	BUILD_MAP         ''
1740	BUILD_TUPLE_2     ''
1743	LOAD_CONST        'chatInitialization'
1746	BUILD_MAP         ''
1749	BUILD_TUPLE_2     ''
1752	LOAD_CONST        'userInviteCommand'
1755	BUILD_MAP         ''
1758	BUILD_TUPLE_2     ''
1761	LOAD_CONST        'createInvite'
1764	BUILD_MAP         ''
1767	BUILD_TUPLE_2     ''
1770	LOAD_CONST        'receiveInvite'
1773	BUILD_MAP         ''
1776	BUILD_TUPLE_2     ''
1779	LOAD_CONST        'receiveArchiveInvite'
1782	BUILD_MAP         ''
1785	BUILD_TUPLE_2     ''
1788	LOAD_CONST        'receiveMembersCount'
1791	BUILD_MAP         ''
1794	BUILD_TUPLE_2     ''
1797	LOAD_CONST        'receiveMembersDelta'
1800	BUILD_MAP         ''
1803	BUILD_TUPLE_2     ''
1806	LOAD_CONST        'VOIPSettings'
1809	BUILD_MAP         ''
1812	BUILD_TUPLE_2     ''
1815	LOAD_CONST        'VOIPCredentials'
1818	BUILD_MAP         ''
1821	BUILD_TUPLE_2     ''
1824	LOAD_CONST        'setMuted'
1827	BUILD_MAP         ''
1830	BUILD_TUPLE_2     ''
1833	LOAD_CONST        'unsetMuted'
1836	BUILD_MAP         ''
1839	BUILD_TUPLE_2     ''
1842	LOAD_CONST        'logVivoxLogin'
1845	BUILD_MAP         ''
1848	BUILD_TUPLE_2     ''
1851	BUILD_LIST_35     ''
1854	LOAD_CONST        'instance'
1857	LOAD_NAME         'AttributeEnumItem'
1860	CALL_FUNCTION_258 ''
1863	STORE_NAME        'CHAT_ACTIONS'
1866_0	COME_FROM         '1527'
1866	LOAD_NAME         'Enumeration'
1869	LOAD_CONST        'chatActionResponses'
1872	LOAD_CONST        ('success', 'internalError', 'channelAlreadyExists', 'channelDestroyed', 'passwordRequired', 'incorrectPassword', 'channelNotExists', 'memberBanned', 'memberDisconnecting', 'notAllowed', 'connectTimeout', 'initializationFailure', 'userNotExists', 'usersRosterLimitReached', 'activeChannelsLimitReached', 'sqlError', 'incorrectCharacter', 'addFriendError', 'addIgnoredError', 'userIgnoredError', 'chatCommandError', 'memberAlreadyBanned', 'memberAlreadyModerator', 'memberNotModerator', 'commandInCooldown', 'createPrivateError', 'actionInCooldown', 'chatBanned', 'inviteCommandError', 'unknownCommand', 'inviteCreateError', 'membersLimitReached', 'notSupported', 'inviteCreationNotAllowed', 'incorrectCommandArgument', 'invalidChannelName', 'setMutedError', 'unsetMutedError')
1875	CALL_FUNCTION_2   ''
1878	STORE_NAME        'CHAT_RESPONSES'
1881	LOAD_CONST        0.5
1884	STORE_NAME        '__DEFAULT_COOLDOWN'
1887	LOAD_NAME         '__DEFAULT_COOLDOWN'
1890	STORE_NAME        '__BATTLE_COMMANDS_DEFAULT_COOLDOWN'
1893	LOAD_CONST        3.0
1896	STORE_NAME        '__CHINA_USER_MESSAGE_COOLDOWN'
1899	LOAD_CONST        1
1902	STORE_NAME        '__COOLDOWN_CHECK_CLIENT'
1905	LOAD_CONST        2
1908	STORE_NAME        '__COOLDOWN_CHECK_BASE'
1911	LOAD_NAME         '__COOLDOWN_CHECK_CLIENT'
1914	LOAD_NAME         '__COOLDOWN_CHECK_BASE'
1917	BINARY_OR         ''
1918	STORE_NAME        '__COOLDOWN_CHECK_ALL'
1921	LOAD_NAME         'Enumeration'
1924	LOAD_CONST        'chatCommands'
1927	LOAD_CONST        'initAck'
1930	BUILD_MAP         ''
1933	LOAD_CONST        ''
1936	LOAD_CONST        'chnlCmd'
1939	STORE_MAP         ''
1940	BUILD_TUPLE_2     ''
1943	LOAD_CONST        'updateMemeberStatus'
1946	BUILD_MAP         ''
1949	LOAD_CONST        ''
1952	LOAD_CONST        'chnlCmd'
1955	STORE_MAP         ''
1956	BUILD_TUPLE_2     ''
1959	LOAD_CONST        'findUser'
1962	BUILD_MAP         ''
1965	LOAD_CONST        ''
1968	LOAD_CONST        'chnlCmd'
1971	STORE_MAP         ''
1972	BUILD_MAP         ''
1975	LOAD_CONST        5.0
1978	LOAD_CONST        'period'
1981	STORE_MAP         ''
1982	LOAD_NAME         '__COOLDOWN_CHECK_ALL'
1985	LOAD_CONST        'side'
1988	STORE_MAP         ''
1989	LOAD_CONST        'cooldown'
1992	STORE_MAP         ''
1993	BUILD_TUPLE_2     ''
1996	LOAD_CONST        'addFriend'
1999	BUILD_MAP         ''
2002	LOAD_CONST        ''
2005	LOAD_CONST        'chnlCmd'
2008	STORE_MAP         ''
2009	BUILD_MAP         ''
2012	LOAD_CONST        5.0
2015	LOAD_CONST        'period'
2018	STORE_MAP         ''
2019	LOAD_NAME         '__COOLDOWN_CHECK_ALL'
2022	LOAD_CONST        'side'
2025	STORE_MAP         ''
2026	LOAD_CONST        'cooldown'
2029	STORE_MAP         ''
2030	BUILD_TUPLE_2     ''
2033	LOAD_CONST        'addIgnored'
2036	BUILD_MAP         ''
2039	LOAD_CONST        ''
2042	LOAD_CONST        'chnlCmd'
2045	STORE_MAP         ''
2046	BUILD_MAP         ''
2049	LOAD_CONST        5.0
2052	LOAD_CONST        'period'
2055	STORE_MAP         ''
2056	LOAD_NAME         '__COOLDOWN_CHECK_ALL'
2059	LOAD_CONST        'side'
2062	STORE_MAP         ''
2063	LOAD_CONST        'cooldown'
2066	STORE_MAP         ''
2067	BUILD_TUPLE_2     ''
2070	LOAD_CONST        'removeFriend'
2073	BUILD_MAP         ''
2076	LOAD_CONST        ''
2079	LOAD_CONST        'chnlCmd'
2082	STORE_MAP         ''
2083	BUILD_MAP         ''
2086	LOAD_CONST        5.0
2089	LOAD_CONST        'period'
2092	STORE_MAP         ''
2093	LOAD_NAME         '__COOLDOWN_CHECK_ALL'
2096	LOAD_CONST        'side'
2099	STORE_MAP         ''
2100	LOAD_CONST        'cooldown'
2103	STORE_MAP         ''
2104	BUILD_TUPLE_2     ''
2107	LOAD_CONST        'removeIgnored'
2110	BUILD_MAP         ''
2113	LOAD_CONST        ''
2116	LOAD_CONST        'chnlCmd'
2119	STORE_MAP         ''
2120	BUILD_MAP         ''
2123	LOAD_CONST        5.0
2126	LOAD_CONST        'period'
2129	STORE_MAP         ''
2130	LOAD_NAME         '__COOLDOWN_CHECK_ALL'
2133	LOAD_CONST        'side'
2136	STORE_MAP         ''
2137	LOAD_CONST        'cooldown'
2140	STORE_MAP         ''
2141	BUILD_TUPLE_2     ''
2144	LOAD_CONST        'createPrivate'
2147	BUILD_MAP         ''
2150	LOAD_CONST        ''
2153	LOAD_CONST        'chnlCmd'
2156	STORE_MAP         ''
2157	BUILD_MAP         ''
2160	LOAD_CONST        5.0
2163	LOAD_CONST        'period'
2166	STORE_MAP         ''
2167	LOAD_NAME         '__COOLDOWN_CHECK_ALL'
2170	LOAD_CONST        'side'
2173	STORE_MAP         ''
2174	LOAD_CONST        'cooldown'
2177	STORE_MAP         ''
2178	BUILD_TUPLE_2     ''
2181	LOAD_CONST        'joinPrivate'
2184	BUILD_MAP         ''
2187	LOAD_CONST        ''
2190	LOAD_CONST        'chnlCmd'
2193	STORE_MAP         ''
2194	BUILD_TUPLE_2     ''
2197	LOAD_CONST        'requestUsersRoster'
2200	BUILD_MAP         ''
2203	LOAD_CONST        ''
2206	LOAD_CONST        'chnlCmd'
2209	STORE_MAP         ''
2210	BUILD_TUPLE_2     ''
2213	LOAD_CONST        'requestFriendStatus'
2216	BUILD_MAP         ''
2219	LOAD_CONST        ''
2222	LOAD_CONST        'chnlCmd'
2225	STORE_MAP         ''
2226	BUILD_TUPLE_2     ''
2229	LOAD_CONST        'friendStatusChange'
2232	BUILD_MAP         ''
2235	LOAD_CONST        ''
2238	LOAD_CONST        'chnlCmd'
2241	STORE_MAP         ''
2242	BUILD_TUPLE_2     ''
2245	LOAD_CONST        'addAdmirer'
2248	BUILD_MAP         ''
2251	LOAD_CONST        ''
2254	LOAD_CONST        'chnlCmd'
2257	STORE_MAP         ''
2258	BUILD_TUPLE_2     ''
2261	LOAD_CONST        'addAdmirerAck'
2264	BUILD_MAP         ''
2267	LOAD_CONST        ''
2270	LOAD_CONST        'chnlCmd'
2273	STORE_MAP         ''
2274	BUILD_TUPLE_2     ''
2277	LOAD_CONST        'removeAdmirer'
2280	BUILD_MAP         ''
2283	LOAD_CONST        ''
2286	LOAD_CONST        'chnlCmd'
2289	STORE_MAP         ''
2290	BUILD_TUPLE_2     ''
2293	LOAD_CONST        'onAddToIgnored'
2296	BUILD_MAP         ''
2299	LOAD_CONST        ''
2302	LOAD_CONST        'chnlCmd'
2305	STORE_MAP         ''
2306	BUILD_TUPLE_2     ''
2309	LOAD_CONST        'CHGCHNLNAME'
2312	BUILD_MAP         ''
2315	LOAD_CONST        1
2318	LOAD_CONST        'chnlCmd'
2321	STORE_MAP         ''
2322	LOAD_CONST        1
2325	LOAD_CONST        'argsCnt'
2328	STORE_MAP         ''
2329	BUILD_MAP         ''
2332	LOAD_CONST        30.0
2335	LOAD_CONST        'period'
2338	STORE_MAP         ''
2339	LOAD_NAME         '__COOLDOWN_CHECK_ALL'
2342	LOAD_CONST        'side'
2345	STORE_MAP         ''
2346	LOAD_CONST        'cooldown'
2349	STORE_MAP         ''
2350	BUILD_TUPLE_2     ''
2353	LOAD_CONST        'GREETING'
2356	BUILD_MAP         ''
2359	LOAD_CONST        1
2362	LOAD_CONST        'chnlCmd'
2365	STORE_MAP         ''
2366	LOAD_CONST        1
2369	LOAD_CONST        'argsCnt'
2372	STORE_MAP         ''
2373	BUILD_MAP         ''
2376	LOAD_CONST        30.0
2379	LOAD_CONST        'period'
2382	STORE_MAP         ''
2383	LOAD_NAME         '__COOLDOWN_CHECK_ALL'
2386	LOAD_CONST        'side'
2389	STORE_MAP         ''
2390	LOAD_CONST        'cooldown'
2393	STORE_MAP         ''
2394	BUILD_TUPLE_2     ''
2397	LOAD_CONST        'BAN'
2400	BUILD_MAP         ''
2403	LOAD_CONST        1
2406	LOAD_CONST        'chnlCmd'
2409	STORE_MAP         ''
2410	LOAD_CONST        3
2413	LOAD_CONST        'argsCnt'
2416	STORE_MAP         ''
2417	BUILD_MAP         ''
2420	LOAD_CONST        10.0
2423	LOAD_CONST        'period'
2426	STORE_MAP         ''
2427	LOAD_NAME         '__COOLDOWN_CHECK_ALL'
2430	LOAD_CONST        'side'
2433	STORE_MAP         ''
2434	LOAD_CONST        'cooldown'
2437	STORE_MAP         ''
2438	BUILD_TUPLE_2     ''
2441	LOAD_CONST        'UNBAN'
2444	BUILD_MAP         ''
2447	LOAD_CONST        1
2450	LOAD_CONST        'chnlCmd'
2453	STORE_MAP         ''
2454	LOAD_CONST        1
2457	LOAD_CONST        'argsCnt'
2460	STORE_MAP         ''
2461	BUILD_MAP         ''
2464	LOAD_CONST        10.0
2467	LOAD_CONST        'period'
2470	STORE_MAP         ''
2471	LOAD_NAME         '__COOLDOWN_CHECK_ALL'
2474	LOAD_CONST        'side'
2477	STORE_MAP         ''
2478	LOAD_CONST        'cooldown'
2481	STORE_MAP         ''
2482	BUILD_TUPLE_2     ''
2485	LOAD_CONST        'ADDMODERATOR'
2488	BUILD_MAP         ''
2491	LOAD_CONST        1
2494	LOAD_CONST        'chnlCmd'
2497	STORE_MAP         ''
2498	LOAD_CONST        1
2501	LOAD_CONST        'argsCnt'
2504	STORE_MAP         ''
2505	BUILD_MAP         ''
2508	LOAD_CONST        10.0
2511	LOAD_CONST        'period'
2514	STORE_MAP         ''
2515	LOAD_NAME         '__COOLDOWN_CHECK_ALL'
2518	LOAD_CONST        'side'
2521	STORE_MAP         ''
2522	LOAD_CONST        'cooldown'
2525	STORE_MAP         ''
2526	BUILD_TUPLE_2     ''
2529	LOAD_CONST        'DELMODERATOR'
2532	BUILD_MAP         ''
2535	LOAD_CONST        1
2538	LOAD_CONST        'chnlCmd'
2541	STORE_MAP         ''
2542	LOAD_CONST        1
2545	LOAD_CONST        'argsCnt'
2548	STORE_MAP         ''
2549	BUILD_MAP         ''
2552	LOAD_CONST        10.0
2555	LOAD_CONST        'period'
2558	STORE_MAP         ''
2559	LOAD_NAME         '__COOLDOWN_CHECK_ALL'
2562	LOAD_CONST        'side'
2565	STORE_MAP         ''
2566	LOAD_CONST        'cooldown'
2569	STORE_MAP         ''
2570	BUILD_TUPLE_2     ''
2573	LOAD_CONST        'HELPME'
2576	BUILD_MAP         ''
2579	LOAD_CONST        1
2582	LOAD_CONST        'battleCmd'
2585	STORE_MAP         ''
2586	LOAD_CONST        ''
2589	LOAD_CONST        'argsCnt'
2592	STORE_MAP         ''
2593	BUILD_MAP         ''
2596	LOAD_CONST        5.0
2599	LOAD_CONST        'period'
2602	STORE_MAP         ''
2603	LOAD_NAME         '__COOLDOWN_CHECK_ALL'
2606	LOAD_CONST        'side'
2609	STORE_MAP         ''
2610	LOAD_CONST        'cooldown'
2613	STORE_MAP         ''
2614	LOAD_CONST        '#ingame_gui:chat_shortcuts/help_me'
2617	LOAD_CONST        'msgText'
2620	STORE_MAP         ''
2621	LOAD_CONST        'help_me'
2624	LOAD_CONST        'vehMarker'
2627	STORE_MAP         ''
2628	LOAD_CONST        'help_me'
2631	LOAD_CONST        'sound_notification'
2634	STORE_MAP         ''
2638	LOAD_CONST        'FOLLOWME'
2641	BUILD_MAP         ''
2644	LOAD_CONST        1
2647	LOAD_CONST        'battleCmd'
2650	STORE_MAP         ''
2651	LOAD_CONST        1
2654	LOAD_CONST        'argsCnt'
2657	STORE_MAP         ''
2658	BUILD_MAP         ''
2661	LOAD_CONST        5.0
2664	LOAD_CONST        'period'
2667	STORE_MAP         ''
2668	LOAD_NAME         '__COOLDOWN_CHECK_ALL'
2671	LOAD_CONST        'side'
2674	STORE_MAP         ''
2675	LOAD_CONST        'cooldown'
2678	STORE_MAP         ''
2679	LOAD_CONST        '#ingame_gui:chat_shortcuts/follow_me'
2682	LOAD_CONST        'msgText'
2685	STORE_MAP         ''
2686	LOAD_CONST        'follow_me'
2689	LOAD_CONST        'vehMarker'
2692	STORE_MAP         ''
2693	LOAD_CONST        'follow_me'
2696	LOAD_CONST        'sound_notification'
2699	STORE_MAP         ''
2703	LOAD_CONST        'ATTACK'
2706	BUILD_MAP         ''
2709	LOAD_CONST        1
2712	LOAD_CONST        'battleCmd'
2715	STORE_MAP         ''
2716	LOAD_CONST        ''
2719	LOAD_CONST        'argsCnt'
2722	STORE_MAP         ''
2723	BUILD_MAP         ''
2726	LOAD_CONST        5.0
2729	LOAD_CONST        'period'
2732	STORE_MAP         ''
2733	LOAD_NAME         '__COOLDOWN_CHECK_ALL'
2736	LOAD_CONST        'side'
2739	STORE_MAP         ''
2740	LOAD_CONST        'cooldown'
2743	STORE_MAP         ''
2744	LOAD_CONST        '#ingame_gui:chat_shortcuts/attack'
2747	LOAD_CONST        'msgText'
2750	STORE_MAP         ''
2751	LOAD_CONST        'attack'
2754	LOAD_CONST        'sound_notification'
2757	STORE_MAP         ''
2761	LOAD_CONST        'BACKTOBASE'
2764	BUILD_MAP         ''
2767	LOAD_CONST        1
2770	LOAD_CONST        'battleCmd'
2773	STORE_MAP         ''
2774	LOAD_CONST        ''
2777	LOAD_CONST        'argsCnt'
2780	STORE_MAP         ''
2781	BUILD_MAP         ''
2784	LOAD_CONST        5.0
2787	LOAD_CONST        'period'
2790	STORE_MAP         ''
2791	LOAD_NAME         '__COOLDOWN_CHECK_ALL'
2794	LOAD_CONST        'side'
2797	STORE_MAP         ''
2798	LOAD_CONST        'cooldown'
2801	STORE_MAP         ''
2802	LOAD_CONST        '#ingame_gui:chat_shortcuts/back_to_base'
2805	LOAD_CONST        'msgText'
2808	STORE_MAP         ''
2809	LOAD_CONST        'back_to_base'
2812	LOAD_CONST        'sound_notification'
2815	STORE_MAP         ''
2819	LOAD_CONST        'POSITIVE'
2822	BUILD_MAP         ''
2825	LOAD_CONST        1
2828	LOAD_CONST        'battleCmd'
2831	STORE_MAP         ''
2832	LOAD_CONST        ''
2835	LOAD_CONST        'argsCnt'
2838	STORE_MAP         ''
2839	BUILD_MAP         ''
2842	LOAD_CONST        5.0
2845	LOAD_CONST        'period'
2848	STORE_MAP         ''
2849	LOAD_NAME         '__COOLDOWN_CHECK_ALL'
2852	LOAD_CONST        'side'
2855	STORE_MAP         ''
2856	LOAD_CONST        'cooldown'
2859	STORE_MAP         ''
2860	LOAD_CONST        '#ingame_gui:chat_shortcuts/positive'
2863	LOAD_CONST        'msgText'
2866	STORE_MAP         ''
2867	LOAD_CONST        'positive'
2870	LOAD_CONST        'vehMarker'
2873	STORE_MAP         ''
2874	LOAD_CONST        'positive'
2877	LOAD_CONST        'sound_notification'
2880	STORE_MAP         ''
2884	LOAD_CONST        'NEGATIVE'
2887	BUILD_MAP         ''
2890	LOAD_CONST        1
2893	LOAD_CONST        'battleCmd'
2896	STORE_MAP         ''
2897	LOAD_CONST        ''
2900	LOAD_CONST        'argsCnt'
2903	STORE_MAP         ''
2904	BUILD_MAP         ''
2907	LOAD_CONST        5.0
2910	LOAD_CONST        'period'
2913	STORE_MAP         ''
2914	LOAD_NAME         '__COOLDOWN_CHECK_ALL'
2917	LOAD_CONST        'side'
2920	STORE_MAP         ''
2921	LOAD_CONST        'cooldown'
2924	STORE_MAP         ''
2925	LOAD_CONST        '#ingame_gui:chat_shortcuts/negative'
2928	LOAD_CONST        'msgText'
2931	STORE_MAP         ''
2932	LOAD_CONST        'negative'
2935	LOAD_CONST        'vehMarker'
2938	STORE_MAP         ''
2939	LOAD_CONST        'negative'
2942	LOAD_CONST        'sound_notification'
2945	STORE_MAP         ''
2949	LOAD_CONST        'ATTENTIONTOCELL'
2952	BUILD_MAP         ''
2955	LOAD_CONST        1
2958	LOAD_CONST        'battleCmd'
2961	STORE_MAP         ''
2962	LOAD_CONST        1
2965	LOAD_CONST        'argsCnt'
2968	STORE_MAP         ''
2969	BUILD_MAP         ''
2972	LOAD_NAME         '__BATTLE_COMMANDS_DEFAULT_COOLDOWN'
2975	LOAD_CONST        'period'
2978	STORE_MAP         ''
2979	LOAD_NAME         '__COOLDOWN_CHECK_ALL'
2982	LOAD_CONST        'side'
2985	STORE_MAP         ''
2986	LOAD_CONST        'cooldown'
2989	STORE_MAP         ''
2990	LOAD_CONST        '#ingame_gui:chat_shortcuts/attention_to_cell'
2993	LOAD_CONST        'msgText'
2996	STORE_MAP         ''
2997	BUILD_TUPLE_2     ''
3000	LOAD_CONST        'ATTACKENEMY'
3003	BUILD_MAP         ''
3006	LOAD_CONST        1
3009	LOAD_CONST        'battleCmd'
3012	STORE_MAP         ''
3013	LOAD_CONST        1
3016	LOAD_CONST        'argsCnt'
3019	STORE_MAP         ''
3020	BUILD_MAP         ''
3023	LOAD_CONST        5.0
3026	LOAD_CONST        'period'
3029	STORE_MAP         ''
3030	LOAD_NAME         '__COOLDOWN_CHECK_ALL'
3033	LOAD_CONST        'side'
3036	STORE_MAP         ''
3037	LOAD_CONST        'cooldown'
3040	STORE_MAP         ''
3041	LOAD_CONST        '#ingame_gui:chat_shortcuts/attack_enemy'
3044	LOAD_CONST        'msgText'
3047	STORE_MAP         ''
3048	LOAD_CONST        'attack'
3051	LOAD_CONST        'vehMarker'
3054	STORE_MAP         ''
3055	LOAD_CONST        'attack_the_enemy'
3058	LOAD_CONST        'sound_notification'
3061	STORE_MAP         ''
3065	LOAD_CONST        'requestLastSysMessages'
3068	BUILD_MAP         ''
3071	LOAD_CONST        ''
3074	LOAD_CONST        'chnlCmd'
3077	STORE_MAP         ''
3078	BUILD_TUPLE_2     ''
3081	LOAD_CONST        'chatAckInitialization'
3084	BUILD_MAP         ''
3087	LOAD_CONST        ''
3090	LOAD_CONST        'chnlCmd'
3093	STORE_MAP         ''
3094	BUILD_TUPLE_2     ''
3097	LOAD_CONST        'createInvite'
3100	BUILD_MAP         ''
3103	LOAD_CONST        1
3106	LOAD_CONST        'inviteCmd'
3109	STORE_MAP         ''
3110	BUILD_MAP         ''
3113	LOAD_CONST        ''
3116	LOAD_CONST        'period'
3119	STORE_MAP         ''
3120	LOAD_NAME         '__COOLDOWN_CHECK_ALL'
3123	LOAD_CONST        'side'
3126	STORE_MAP         ''
3127	LOAD_CONST        'cooldown'
3130	STORE_MAP         ''
3131	BUILD_TUPLE_2     ''
3134	LOAD_CONST        'inviteReceived'
3137	BUILD_MAP         ''
3140	LOAD_CONST        1
3143	LOAD_CONST        'inviteCmd'
3146	STORE_MAP         ''
3147	BUILD_TUPLE_2     ''
3150	LOAD_CONST        'acceptInvite'
3153	BUILD_MAP         ''
3156	LOAD_CONST        1
3159	LOAD_CONST        'inviteCmd'
3162	STORE_MAP         ''
3163	BUILD_MAP         ''
3166	LOAD_CONST        5.0
3169	LOAD_CONST        'period'
3172	STORE_MAP         ''
3173	LOAD_NAME         '__COOLDOWN_CHECK_ALL'
3176	LOAD_CONST        'side'
3179	STORE_MAP         ''
3180	LOAD_CONST        'cooldown'
3183	STORE_MAP         ''
3184	BUILD_TUPLE_2     ''
3187	LOAD_CONST        'rejectInvite'
3190	BUILD_MAP         ''
3193	LOAD_CONST        1
3196	LOAD_CONST        'inviteCmd'
3199	STORE_MAP         ''
3200	BUILD_MAP         ''
3203	LOAD_CONST        5.0
3206	LOAD_CONST        'period'
3209	STORE_MAP         ''
3210	LOAD_NAME         '__COOLDOWN_CHECK_ALL'
3213	LOAD_CONST        'side'
3216	STORE_MAP         ''
3217	LOAD_CONST        'cooldown'
3220	STORE_MAP         ''
3221	BUILD_TUPLE_2     ''
3224	LOAD_CONST        'getActiveInvites'
3227	BUILD_MAP         ''
3230	LOAD_CONST        1
3233	LOAD_CONST        'inviteCmd'
3236	STORE_MAP         ''
3237	BUILD_MAP         ''
3240	LOAD_CONST        5.0
3243	LOAD_CONST        'period'
3246	STORE_MAP         ''
3247	LOAD_NAME         '__COOLDOWN_CHECK_ALL'
3250	LOAD_CONST        'side'
3253	STORE_MAP         ''
3254	LOAD_CONST        'cooldown'
3257	STORE_MAP         ''
3258	BUILD_TUPLE_2     ''
3261	LOAD_CONST        'getArchiveInvites'
3264	BUILD_MAP         ''
3267	LOAD_CONST        1
3270	LOAD_CONST        'inviteCmd'
3273	STORE_MAP         ''
3274	BUILD_MAP         ''
3277	LOAD_CONST        5.0
3280	LOAD_CONST        'period'
3283	STORE_MAP         ''
3284	LOAD_NAME         '__COOLDOWN_CHECK_ALL'
3287	LOAD_CONST        'side'
3290	STORE_MAP         ''
3291	LOAD_CONST        'cooldown'
3294	STORE_MAP         ''
3295	BUILD_TUPLE_2     ''
3298	LOAD_CONST        'getMembersCount'
3301	BUILD_MAP         ''
3304	LOAD_CONST        1
3307	LOAD_CONST        'chnlCmd'
3310	STORE_MAP         ''
3311	BUILD_MAP         ''
3314	LOAD_NAME         '__DEFAULT_COOLDOWN'
3317	LOAD_CONST        'period'
3320	STORE_MAP         ''
3321	LOAD_NAME         '__COOLDOWN_CHECK_ALL'
3324	LOAD_CONST        'side'
3327	STORE_MAP         ''
3328	LOAD_CONST        'cooldown'
3331	STORE_MAP         ''
3332	BUILD_TUPLE_2     ''
3335	LOAD_CONST        'requestSystemChatChannels'
3338	BUILD_MAP         ''
3341	LOAD_CONST        ''
3344	LOAD_CONST        'chnlCmd'
3347	STORE_MAP         ''
3348	BUILD_MAP         ''
3351	LOAD_NAME         '__DEFAULT_COOLDOWN'
3354	LOAD_CONST        'period'
3357	STORE_MAP         ''
3358	LOAD_NAME         '__COOLDOWN_CHECK_ALL'
3361	LOAD_CONST        'side'
3364	STORE_MAP         ''
3365	LOAD_CONST        'cooldown'
3368	STORE_MAP         ''
3369	BUILD_TUPLE_2     ''
3372	LOAD_CONST        'findChatChannels'
3375	BUILD_MAP         ''
3378	LOAD_CONST        ''
3381	LOAD_CONST        'chnlCmd'
3384	STORE_MAP         ''
3385	BUILD_MAP         ''
3388	LOAD_CONST        5.0
3391	LOAD_CONST        'period'
3394	STORE_MAP         ''
3395	LOAD_NAME         '__COOLDOWN_CHECK_ALL'
3398	LOAD_CONST        'side'
3401	STORE_MAP         ''
3402	LOAD_CONST        'cooldown'
3405	STORE_MAP         ''
3406	BUILD_TUPLE_2     ''
3409	LOAD_CONST        'getChannelInfoById'
3412	BUILD_MAP         ''
3415	LOAD_CONST        ''
3418	LOAD_CONST        'chnlCmd'
3421	STORE_MAP         ''
3422	BUILD_TUPLE_2     ''
3425	LOAD_CONST        'createChatChannel'
3428	BUILD_MAP         ''
3431	LOAD_CONST        ''
3434	LOAD_CONST        'chnlCmd'
3437	STORE_MAP         ''
3438	BUILD_MAP         ''
3441	LOAD_CONST        10.0
3444	LOAD_CONST        'period'
3447	STORE_MAP         ''
3448	LOAD_NAME         '__COOLDOWN_CHECK_ALL'
3451	LOAD_CONST        'side'
3454	STORE_MAP         ''
3455	LOAD_CONST        'cooldown'
3458	STORE_MAP         ''
3459	BUILD_TUPLE_2     ''
3462	LOAD_CONST        'destroyChatChannel'
3465	BUILD_MAP         ''
3468	LOAD_CONST        ''
3471	LOAD_CONST        'chnlCmd'
3474	STORE_MAP         ''
3475	BUILD_TUPLE_2     ''
3478	LOAD_CONST        'requestChatChannelMembers'
3481	BUILD_MAP         ''
3484	LOAD_CONST        1
3487	LOAD_CONST        'chnlCmd'
3490	STORE_MAP         ''
3491	LOAD_CONST        1
3494	LOAD_CONST        'skipBanCheck'
3497	STORE_MAP         ''
3498	BUILD_MAP         ''
3501	LOAD_CONST        2.0
3504	LOAD_CONST        'period'
3507	STORE_MAP         ''
3508	LOAD_CONST        ''
3511	LOAD_CONST        'side'
3514	STORE_MAP         ''
3515	LOAD_CONST        'cooldown'
3518	STORE_MAP         ''
3519	BUILD_TUPLE_2     ''
3522	LOAD_CONST        'enterChatChannel'
3525	BUILD_MAP         ''
3528	LOAD_CONST        ''
3531	LOAD_CONST        'chnlCmd'
3534	STORE_MAP         ''
3535	BUILD_MAP         ''
3538	LOAD_NAME         '__DEFAULT_COOLDOWN'
3541	LOAD_CONST        'period'
3544	STORE_MAP         ''
3545	LOAD_CONST        ''
3548	LOAD_CONST        'side'
3551	STORE_MAP         ''
3552	LOAD_CONST        'cooldown'
3555	STORE_MAP         ''
3556	BUILD_TUPLE_2     ''
3559	LOAD_CONST        'leaveChatChannel'
3562	BUILD_MAP         ''
3565	LOAD_CONST        ''
3568	LOAD_CONST        'chnlCmd'
3571	STORE_MAP         ''
3572	BUILD_MAP         ''
3575	LOAD_NAME         '__DEFAULT_COOLDOWN'
3578	LOAD_CONST        'period'
3581	STORE_MAP         ''
3582	LOAD_CONST        ''
3585	LOAD_CONST        'side'
3588	STORE_MAP         ''
3589	LOAD_CONST        'cooldown'
3592	STORE_MAP         ''
3593	BUILD_TUPLE_2     ''
3596	LOAD_CONST        'broadcast'
3599	BUILD_MAP         ''
3602	LOAD_CONST        ''
3605	LOAD_CONST        'chnlCmd'
3608	STORE_MAP         ''
3609	BUILD_MAP         ''
3612	LOAD_NAME         'constants'
3615	LOAD_ATTR         'IS_CHINA'
3618	POP_JUMP_IF_TRUE  '3627'
3621	LOAD_NAME         '__DEFAULT_COOLDOWN'
3624	JUMP_FORWARD      '3630'
3627	LOAD_NAME         '__CHINA_USER_MESSAGE_COOLDOWN'
3630_0	COME_FROM         '3624'
3630	LOAD_CONST        'period'
3633	STORE_MAP         ''
3634	LOAD_NAME         '__COOLDOWN_CHECK_ALL'
3637	LOAD_CONST        'side'
3640	STORE_MAP         ''
3641	LOAD_CONST        'cooldown'
3644	STORE_MAP         ''
3645	BUILD_TUPLE_2     ''
3648	LOAD_CONST        'USERBAN'
3651	BUILD_MAP         ''
3654	LOAD_CONST        1
3657	LOAD_CONST        'userCmd'
3660	STORE_MAP         ''
3661	LOAD_CONST        4
3664	LOAD_CONST        'argsCnt'
3667	STORE_MAP         ''
3668	BUILD_MAP         ''
3671	LOAD_CONST        5.0
3674	LOAD_CONST        'period'
3677	STORE_MAP         ''
3678	LOAD_NAME         '__COOLDOWN_CHECK_ALL'
3681	LOAD_CONST        'side'
3684	STORE_MAP         ''
3685	LOAD_CONST        'cooldown'
3688	STORE_MAP         ''
3689	BUILD_TUPLE_2     ''
3692	LOAD_CONST        'USERUNBAN'
3695	BUILD_MAP         ''
3698	LOAD_CONST        1
3701	LOAD_CONST        'userCmd'
3704	STORE_MAP         ''
3705	LOAD_CONST        2
3708	LOAD_CONST        'argsCnt'
3711	STORE_MAP         ''
3712	BUILD_MAP         ''
3715	LOAD_CONST        5.0
3718	LOAD_CONST        'period'
3721	STORE_MAP         ''
3722	LOAD_NAME         '__COOLDOWN_CHECK_ALL'
3725	LOAD_CONST        'side'
3728	STORE_MAP         ''
3729	LOAD_CONST        'cooldown'
3732	STORE_MAP         ''
3733	BUILD_TUPLE_2     ''
3736	LOAD_CONST        'requestVOIPSettings'
3739	BUILD_MAP         ''
3742	LOAD_CONST        1
3745	LOAD_CONST        'chnlCmd'
3748	STORE_MAP         ''
3749	LOAD_CONST        1
3752	LOAD_CONST        'skipBanCheck'
3755	STORE_MAP         ''
3756	BUILD_MAP         ''
3759	LOAD_NAME         '__DEFAULT_COOLDOWN'
3762	LOAD_CONST        'period'
3765	STORE_MAP         ''
3766	LOAD_NAME         '__COOLDOWN_CHECK_ALL'
3769	LOAD_CONST        'side'
3772	STORE_MAP         ''
3773	LOAD_CONST        'cooldown'
3776	STORE_MAP         ''
3777	BUILD_TUPLE_2     ''
3780	LOAD_CONST        'requestVOIPCredentials'
3783	BUILD_MAP         ''
3786	LOAD_CONST        ''
3789	LOAD_CONST        'chnlCmd'
3792	STORE_MAP         ''
3793	LOAD_CONST        1
3796	LOAD_CONST        'skipBanCheck'
3799	STORE_MAP         ''
3800	BUILD_TUPLE_2     ''
3803	LOAD_CONST        'setMuted'
3806	BUILD_MAP         ''
3809	LOAD_CONST        ''
3812	LOAD_CONST        'chnlCmd'
3815	STORE_MAP         ''
3816	BUILD_MAP         ''
3819	LOAD_CONST        5.0
3822	LOAD_CONST        'period'
3825	STORE_MAP         ''
3826	LOAD_NAME         '__COOLDOWN_CHECK_ALL'
3829	LOAD_CONST        'side'
3832	STORE_MAP         ''
3833	LOAD_CONST        'cooldown'
3836	STORE_MAP         ''
3837	BUILD_TUPLE_2     ''
3840	LOAD_CONST        'unsetMuted'
3843	BUILD_MAP         ''
3846	LOAD_CONST        ''
3849	LOAD_CONST        'chnlCmd'
3852	STORE_MAP         ''
3853	BUILD_MAP         ''
3856	LOAD_CONST        5.0
3859	LOAD_CONST        'period'
3862	STORE_MAP         ''
3863	LOAD_NAME         '__COOLDOWN_CHECK_ALL'
3866	LOAD_CONST        'side'
3869	STORE_MAP         ''
3870	LOAD_CONST        'cooldown'
3873	STORE_MAP         ''
3874	BUILD_TUPLE_2     ''
3877	LOAD_CONST        'logVivoxLogin'
3880	BUILD_MAP         ''
3883	LOAD_CONST        ''
3886	LOAD_CONST        'chnlCmd'
3889	STORE_MAP         ''
3890	BUILD_MAP         ''
3893	LOAD_NAME         '__DEFAULT_COOLDOWN'
3896	LOAD_CONST        'period'
3899	STORE_MAP         ''
3900	LOAD_NAME         '__COOLDOWN_CHECK_ALL'
3903	LOAD_CONST        'side'
3906	STORE_MAP         ''
3907	LOAD_CONST        'cooldown'
3910	STORE_MAP         ''
3911	BUILD_TUPLE_2     ''
3914	LOAD_CONST        'TURNBACK'
3917	BUILD_MAP         ''
3920	LOAD_CONST        1
3923	LOAD_CONST        'battleCmd'
3926	STORE_MAP         ''
3927	LOAD_CONST        1
3930	LOAD_CONST        'argsCnt'
3933	STORE_MAP         ''
3934	BUILD_MAP         ''
3937	LOAD_CONST        5.0
3940	LOAD_CONST        'period'
3943	STORE_MAP         ''
3944	LOAD_NAME         '__COOLDOWN_CHECK_ALL'
3947	LOAD_CONST        'side'
3950	STORE_MAP         ''
3951	LOAD_CONST        'cooldown'
3954	STORE_MAP         ''
3955	LOAD_CONST        '#ingame_gui:chat_shortcuts/turn_back'
3958	LOAD_CONST        'msgText'
3961	STORE_MAP         ''
3962	LOAD_CONST        'turn_back'
3965	LOAD_CONST        'vehMarker'
3968	STORE_MAP         ''
3969	LOAD_CONST        'turn_back'
3972	LOAD_CONST        'sound_notification'
3975	STORE_MAP         ''
3979	LOAD_CONST        'HELPMEEX'
3982	BUILD_MAP         ''
3985	LOAD_CONST        1
3988	LOAD_CONST        'battleCmd'
3991	STORE_MAP         ''
3992	LOAD_CONST        1
3995	LOAD_CONST        'argsCnt'
3998	STORE_MAP         ''
3999	BUILD_MAP         ''
4002	LOAD_CONST        5.0
4005	LOAD_CONST        'period'
4008	STORE_MAP         ''
4009	LOAD_NAME         '__COOLDOWN_CHECK_ALL'
4012	LOAD_CONST        'side'
4015	STORE_MAP         ''
4016	LOAD_CONST        'cooldown'
4019	STORE_MAP         ''
4020	LOAD_CONST        '#ingame_gui:chat_shortcuts/help_me_ex'
4023	LOAD_CONST        'msgText'
4026	STORE_MAP         ''
4027	LOAD_CONST        'help_me_ex'
4030	LOAD_CONST        'vehMarker'
4033	STORE_MAP         ''
4034	LOAD_CONST        'help_me_ex'
4037	LOAD_CONST        'sound_notification'
4040	STORE_MAP         ''
4044	LOAD_CONST        'SUPPORTMEWITHFIRE'
4047	BUILD_MAP         ''
4050	LOAD_CONST        1
4053	LOAD_CONST        'battleCmd'
4056	STORE_MAP         ''
4057	LOAD_CONST        1
4060	LOAD_CONST        'argsCnt'
4063	STORE_MAP         ''
4064	BUILD_MAP         ''
4067	LOAD_CONST        5.0
4070	LOAD_CONST        'period'
4073	STORE_MAP         ''
4074	LOAD_NAME         '__COOLDOWN_CHECK_ALL'
4077	LOAD_CONST        'side'
4080	STORE_MAP         ''
4081	LOAD_CONST        'cooldown'
4084	STORE_MAP         ''
4085	LOAD_CONST        '#ingame_gui:chat_shortcuts/support_me_with_fire'
4088	LOAD_CONST        'msgText'
4091	STORE_MAP         ''
4092	LOAD_CONST        'attack'
4095	LOAD_CONST        'vehMarker'
4098	STORE_MAP         ''
4099	LOAD_CONST        'support_me_with_fire'
4102	LOAD_CONST        'sound_notification'
4105	STORE_MAP         ''
4109	LOAD_CONST        'RELOADINGGUN'
4112	BUILD_MAP         ''
4115	LOAD_CONST        1
4118	LOAD_CONST        'battleCmd'
4121	STORE_MAP         ''
4122	LOAD_CONST        1
4125	LOAD_CONST        'argsCnt'
4128	STORE_MAP         ''
4129	BUILD_MAP         ''
4132	LOAD_CONST        5.0
4135	LOAD_CONST        'period'
4138	STORE_MAP         ''
4139	LOAD_NAME         '__COOLDOWN_CHECK_ALL'
4142	LOAD_CONST        'side'
4145	STORE_MAP         ''
4146	LOAD_CONST        'cooldown'
4149	STORE_MAP         ''
4150	LOAD_CONST        '#ingame_gui:chat_shortcuts/reloading_gun'
4153	LOAD_CONST        'msgText'
4156	STORE_MAP         ''
4157	LOAD_CONST        'reloading_gun'
4160	LOAD_CONST        'vehMarker'
4163	STORE_MAP         ''
4164	LOAD_CONST        'reloading_gun'
4167	LOAD_CONST        'sound_notification'
4170	STORE_MAP         ''
4174	LOAD_CONST        'STOP'
4177	BUILD_MAP         ''
4180	LOAD_CONST        1
4183	LOAD_CONST        'battleCmd'
4186	STORE_MAP         ''
4187	LOAD_CONST        1
4190	LOAD_CONST        'argsCnt'
4193	STORE_MAP         ''
4194	BUILD_MAP         ''
4197	LOAD_CONST        5.0
4200	LOAD_CONST        'period'
4203	STORE_MAP         ''
4204	LOAD_NAME         '__COOLDOWN_CHECK_ALL'
4207	LOAD_CONST        'side'
4210	STORE_MAP         ''
4211	LOAD_CONST        'cooldown'
4214	STORE_MAP         ''
4215	LOAD_CONST        '#ingame_gui:chat_shortcuts/stop'
4218	LOAD_CONST        'msgText'
4221	STORE_MAP         ''
4222	LOAD_CONST        'stop'
4225	LOAD_CONST        'vehMarker'
4228	STORE_MAP         ''
4229	LOAD_CONST        'stop'
4232	LOAD_CONST        'sound_notification'
4235	STORE_MAP         ''
4239	LOAD_CONST        'RELOADING_CASSETE'
4242	BUILD_MAP         ''
4245	LOAD_CONST        1
4248	LOAD_CONST        'battleCmd'
4251	STORE_MAP         ''
4252	LOAD_CONST        2
4255	LOAD_CONST        'argsCnt'
4258	STORE_MAP         ''
4259	BUILD_MAP         ''
4262	LOAD_CONST        5.0
4265	LOAD_CONST        'period'
4268	STORE_MAP         ''
4269	LOAD_NAME         '__COOLDOWN_CHECK_ALL'
4272	LOAD_CONST        'side'
4275	STORE_MAP         ''
4276	LOAD_CONST        'cooldown'
4279	STORE_MAP         ''
4280	LOAD_CONST        '#ingame_gui:chat_shortcuts/reloading_cassette'
4283	LOAD_CONST        'msgText'
4286	STORE_MAP         ''
4287	LOAD_CONST        'reloading_gun'
4290	LOAD_CONST        'vehMarker'
4293	STORE_MAP         ''
4294	LOAD_CONST        'reloading_gun'
4297	LOAD_CONST        'sound_notification'
4300	STORE_MAP         ''
4304	LOAD_CONST        'RELOADING_READY'
4307	BUILD_MAP         ''
4310	LOAD_CONST        1
4313	LOAD_CONST        'battleCmd'
4316	STORE_MAP         ''
4317	LOAD_CONST        ''
4320	LOAD_CONST        'argsCnt'
4323	STORE_MAP         ''
4324	BUILD_MAP         ''
4327	LOAD_CONST        5.0
4330	LOAD_CONST        'period'
4333	STORE_MAP         ''
4334	LOAD_NAME         '__COOLDOWN_CHECK_ALL'
4337	LOAD_CONST        'side'
4340	STORE_MAP         ''
4341	LOAD_CONST        'cooldown'
4344	STORE_MAP         ''
4345	LOAD_CONST        '#ingame_gui:chat_shortcuts/reloading_ready'
4348	LOAD_CONST        'msgText'
4351	STORE_MAP         ''
4352	BUILD_TUPLE_2     ''
4355	LOAD_CONST        'RELOADING_READY_CASSETE'
4358	BUILD_MAP         ''
4361	LOAD_CONST        1
4364	LOAD_CONST        'battleCmd'
4367	STORE_MAP         ''
4368	LOAD_CONST        1
4371	LOAD_CONST        'argsCnt'
4374	STORE_MAP         ''
4375	BUILD_MAP         ''
4378	LOAD_CONST        5.0
4381	LOAD_CONST        'period'
4384	STORE_MAP         ''
4385	LOAD_NAME         '__COOLDOWN_CHECK_ALL'
4388	LOAD_CONST        'side'
4391	STORE_MAP         ''
4392	LOAD_CONST        'cooldown'
4395	STORE_MAP         ''
4396	LOAD_CONST        '#ingame_gui:chat_shortcuts/reloading_ready_cassette'
4399	LOAD_CONST        'msgText'
4402	STORE_MAP         ''
4403	BUILD_TUPLE_2     ''
4406	LOAD_CONST        'RELOADING_UNAVAILABLE'
4409	BUILD_MAP         ''
4412	LOAD_CONST        1
4415	LOAD_CONST        'battleCmd'
4418	STORE_MAP         ''
4419	LOAD_CONST        ''
4422	LOAD_CONST        'argsCnt'
4425	STORE_MAP         ''
4426	BUILD_MAP         ''
4429	LOAD_CONST        5.0
4432	LOAD_CONST        'period'
4435	STORE_MAP         ''
4436	LOAD_NAME         '__COOLDOWN_CHECK_ALL'
4439	LOAD_CONST        'side'
4442	STORE_MAP         ''
4443	LOAD_CONST        'cooldown'
4446	STORE_MAP         ''
4447	LOAD_CONST        '#ingame_gui:chat_shortcuts/reloading_unavailable'
4450	LOAD_CONST        'msgText'
4453	STORE_MAP         ''
4454	BUILD_TUPLE_2     ''
4457	BUILD_LIST_64     ''
4460	LOAD_CONST        'instance'
4463	LOAD_NAME         'AttributeEnumItem'
4466	CALL_FUNCTION_258 ''
4469	STORE_NAME        'CHAT_COMMANDS'
4472	LOAD_NAME         'Enumeration'
4475	LOAD_CONST        'chatMemberStatuses'
4478	LOAD_CONST        'available'
4481	LOAD_CONST        'inBattle'
4484	BUILD_LIST_2      ''
4487	CALL_FUNCTION_2   ''
4490	STORE_NAME        'CHAT_MEMBER_STATUSES'
4493	LOAD_NAME         'Enumeration'
4496	LOAD_CONST        'chatMemberBanType'
4499	LOAD_CONST        'none'
4502	LOAD_CONST        'readonly'
4505	LOAD_CONST        'full'
4508	BUILD_LIST_3      ''
4511	CALL_FUNCTION_2   ''
4514	STORE_NAME        'CHAT_MEMBER_BAN_TYPE'
4517	LOAD_NAME         'Enumeration'
4520	LOAD_CONST        'chatMemberRole'
4523	LOAD_CONST        'member'
4526	LOAD_CONST        'visitor'
4529	LOAD_CONST        'moderator'
4532	BUILD_LIST_3      ''
4535	CALL_FUNCTION_2   ''
4538	STORE_NAME        'CHAT_MEMBER_ROLE'
4541	LOAD_NAME         'Enumeration'
4544	LOAD_CONST        'chatMemberRole'
4547	LOAD_CONST        'member'
4550	LOAD_CONST        'channelOwner'
4553	LOAD_CONST        'channelModerator'
4556	LOAD_CONST        'chatAdmin'
4559	BUILD_LIST_4      ''
4562	CALL_FUNCTION_2   ''
4565	STORE_NAME        'CHAT_MEMBER_GROUP'
4568	LOAD_CONST        1
4571	STORE_NAME        'CHAT_CHANNEL_BATTLE_TEAM'
4574	LOAD_CONST        2
4577	STORE_NAME        'CHAT_CHANNEL_BATTLE'
4580	LOAD_CONST        4
4583	STORE_NAME        'CHAT_CHANNEL_PREBATTLE'
4586	LOAD_CONST        8
4589	STORE_NAME        'CHAT_CHANNEL_PRIVATE'
4592	LOAD_CONST        16
4595	STORE_NAME        'CHAT_CHANNEL_DESTROYING'
4598	LOAD_CONST        32
4601	STORE_NAME        'CHAT_CHANNEL_TRAINING'
4604	LOAD_CONST        64
4607	STORE_NAME        'CHAT_CHANNEL_SQUAD'
4610	LOAD_CONST        128
4613	STORE_NAME        'CHAT_CHANNEL_TEAM'
4616	LOAD_CONST        256
4619	STORE_NAME        'CHAT_CHANNEL_VOICE'
4622	LOAD_CONST        512
4625	STORE_NAME        'CHAT_CHANNEL_CLAN'
4628	LOAD_CONST        1024
4631	STORE_NAME        'CHAT_CHANNEL_PREBATTLE_CLAN'
4634	LOAD_CONST        2048
4637	STORE_NAME        'CHAT_CHANNEL_TOURNAMENT'
4640	LOAD_CONST        4096
4643	STORE_NAME        'CHAT_CHANNEL_UNIT'
4646	LOAD_CONST        3
4649	STORE_NAME        'CHAT_CHANNEL_NOTIFY_MEMBERS_MASK'
4652	LOAD_CONST        ''
4655	STORE_NAME        'CHAT_CHANNEL_NOTIFY_MEMBERS_IN_OUT'
4658	LOAD_CONST        1
4661	STORE_NAME        'CHAT_CHANNEL_NOT_NOTIFY_MEMBERS_IN_OUT'
4664	LOAD_CONST        2
4667	STORE_NAME        'CHAT_CHANNEL_NOTIFY_MEMBERS_COUNT'
4670	LOAD_CONST        3
4673	STORE_NAME        'CHAT_CHANNEL_NOTIFY_MEMBERS_DELTA'
4676	LOAD_CONST        '<code_object boundActionResponseFilter>'
4679	MAKE_FUNCTION_0   ''
4682	STORE_NAME        'boundActionResponseFilter'
4685	LOAD_CONST        ''
4688	LOAD_CONST        '<code_object buildChatActionData>'
4691	MAKE_FUNCTION_1   ''
4694	STORE_NAME        'buildChatActionData'
4697	LOAD_CONST        'chatChannel_'
4700	STORE_NAME        'ChatChannelKeyPrefix'
4703	LOAD_CONST        '<code_object buildChannelsKey>'
4706	MAKE_FUNCTION_0   ''
4709	STORE_NAME        'buildChannelsKey'
4712	LOAD_NAME         'noexcept'
4715	LOAD_CONST        '<code_object getChannelsIDFromKey>'
4718	MAKE_FUNCTION_0   ''
4721	CALL_FUNCTION_1   ''
4724	STORE_NAME        'getChannelsIDFromKey'
4727	LOAD_CONST        '<code_object isChannelSecured>'
4730	MAKE_FUNCTION_0   ''
4733	STORE_NAME        'isChannelSecured'
4736	LOAD_NAME         'True'
4739	LOAD_CONST        '<code_object _testChannelFlag>'
4742	MAKE_FUNCTION_1   ''
4745	STORE_NAME        '_testChannelFlag'
4748	LOAD_CONST        '<code_object _testFlags>'
4751	MAKE_FUNCTION_0   ''
4754	STORE_NAME        '_testFlags'
4757	LOAD_CONST        '<code_object isChannelDestroying>'
4760	MAKE_FUNCTION_0   ''
4763	STORE_NAME        'isChannelDestroying'
4766	LOAD_CONST        '<code_object isChannelDestroyingFlags>'
4769	MAKE_FUNCTION_0   ''
4772	STORE_NAME        'isChannelDestroyingFlags'
4775	LOAD_CONST        '<code_object isPrivateChannel>'
4778	MAKE_FUNCTION_0   ''
4781	STORE_NAME        'isPrivateChannel'
4784	LOAD_CONST        '<code_object isTrainingChannel>'
4787	MAKE_FUNCTION_0   ''
4790	STORE_NAME        'isTrainingChannel'
4793	LOAD_CONST        '<code_object isPrebattleChannel>'
4796	MAKE_FUNCTION_0   ''
4799	STORE_NAME        'isPrebattleChannel'
4802	LOAD_CONST        '<code_object isPrebattleChannelFlags>'
4805	MAKE_FUNCTION_0   ''
4808	STORE_NAME        'isPrebattleChannelFlags'
4811	LOAD_CONST        '<code_object isSquadChannel>'
4814	MAKE_FUNCTION_0   ''
4817	STORE_NAME        'isSquadChannel'
4820	LOAD_CONST        '<code_object isTeamChannel>'
4823	MAKE_FUNCTION_0   ''
4826	STORE_NAME        'isTeamChannel'
4829	LOAD_CONST        '<code_object isBattleTeamFlags>'
4832	MAKE_FUNCTION_0   ''
4835	STORE_NAME        'isBattleTeamFlags'
4838	LOAD_CONST        '<code_object isArenaBattleTeamFlags>'
4841	MAKE_FUNCTION_0   ''
4844	STORE_NAME        'isArenaBattleTeamFlags'
4847	LOAD_CONST        '<code_object isChannelHasVoice>'
4850	MAKE_FUNCTION_0   ''
4853	STORE_NAME        'isChannelHasVoice'
4856	LOAD_CONST        '<code_object isChannelHasVoiceFlags>'
4859	MAKE_FUNCTION_0   ''
4862	STORE_NAME        'isChannelHasVoiceFlags'
4865	LOAD_CONST        '<code_object isClanChannel>'
4868	MAKE_FUNCTION_0   ''
4871	STORE_NAME        'isClanChannel'
4874	LOAD_CONST        '<code_object isClanChannelFlags>'
4877	MAKE_FUNCTION_0   ''
4880	STORE_NAME        'isClanChannelFlags'
4883	LOAD_CONST        '<code_object isTournamentChannelFlags>'
4886	MAKE_FUNCTION_0   ''
4889	STORE_NAME        'isTournamentChannelFlags'
4892	LOAD_CONST        '<code_object isPrebattleClanChannelFlags>'
4895	MAKE_FUNCTION_0   ''
4898	STORE_NAME        'isPrebattleClanChannelFlags'
4901	LOAD_CONST        '<code_object isRegularChannel>'
4904	MAKE_FUNCTION_0   ''
4907	STORE_NAME        'isRegularChannel'
4910	LOAD_CONST        '<code_object isRegularChannelFlags>'
4913	MAKE_FUNCTION_0   ''
4916	STORE_NAME        'isRegularChannelFlags'
4919	LOAD_CONST        'BaseChatCommandProcessor'
4922	LOAD_NAME         'object'
4925	BUILD_TUPLE_1     ''
4928	LOAD_CONST        '<code_object BaseChatCommandProcessor>'
4931	MAKE_FUNCTION_0   ''
4934	CALL_FUNCTION_0   ''
4937	BUILD_CLASS       ''
4938	STORE_NAME        'BaseChatCommandProcessor'
4941	LOAD_CONST        'OneStringArgCommandProcessor'
4944	LOAD_NAME         'BaseChatCommandProcessor'
4947	BUILD_TUPLE_1     ''
4950	LOAD_CONST        '<code_object OneStringArgCommandProcessor>'
4953	MAKE_FUNCTION_0   ''
4956	CALL_FUNCTION_0   ''
4959	BUILD_CLASS       ''
4960	STORE_NAME        'OneStringArgCommandProcessor'
4963	LOAD_CONST        'NoArgsCommandProcessor'
4966	LOAD_NAME         'BaseChatCommandProcessor'
4969	BUILD_TUPLE_1     ''
4972	LOAD_CONST        '<code_object NoArgsCommandProcessor>'
4975	MAKE_FUNCTION_0   ''
4978	CALL_FUNCTION_0   ''
4981	BUILD_CLASS       ''
4982	STORE_NAME        'NoArgsCommandProcessor'
4985	LOAD_CONST        'BanCommandProcessor'
4988	LOAD_NAME         'BaseChatCommandProcessor'
4991	BUILD_TUPLE_1     ''
4994	LOAD_CONST        '<code_object BanCommandProcessor>'
4997	MAKE_FUNCTION_0   ''
5000	CALL_FUNCTION_0   ''
5003	BUILD_CLASS       ''
5004	STORE_NAME        'BanCommandProcessor'
5007	LOAD_CONST        'UserCommandProcessor'
5010	LOAD_NAME         'BaseChatCommandProcessor'
5013	BUILD_TUPLE_1     ''
5016	LOAD_CONST        '<code_object UserCommandProcessor>'
5019	MAKE_FUNCTION_0   ''
5022	CALL_FUNCTION_0   ''
5025	BUILD_CLASS       ''
5026	STORE_NAME        'UserCommandProcessor'
5029	LOAD_CONST        'UserBanCommandProcessor'
5032	LOAD_NAME         'UserCommandProcessor'
5035	BUILD_TUPLE_1     ''
5038	LOAD_CONST        '<code_object UserBanCommandProcessor>'
5041	MAKE_FUNCTION_0   ''
5044	CALL_FUNCTION_0   ''
5047	BUILD_CLASS       ''
5048	STORE_NAME        'UserBanCommandProcessor'
5051	LOAD_CONST        'UserUnbanCommandProcessor'
5054	LOAD_NAME         'UserCommandProcessor'
5057	BUILD_TUPLE_1     ''
5060	LOAD_CONST        '<code_object UserUnbanCommandProcessor>'
5063	MAKE_FUNCTION_0   ''
5066	CALL_FUNCTION_0   ''
5069	BUILD_CLASS       ''
5070	STORE_NAME        'UserUnbanCommandProcessor'
5073	BUILD_MAP         ''
5076	LOAD_NAME         'BanCommandProcessor'
5079	CALL_FUNCTION_0   ''
5082	LOAD_NAME         'CHAT_COMMANDS'
5085	LOAD_ATTR         'BAN'
5088	STORE_MAP         ''
5089	LOAD_NAME         'OneStringArgCommandProcessor'
5092	LOAD_NAME         'CHAT_COMMANDS'
5095	LOAD_ATTR         'CHGCHNLNAME'
5098	CALL_FUNCTION_1   ''
5101	LOAD_NAME         'CHAT_COMMANDS'
5104	LOAD_ATTR         'CHGCHNLNAME'
5107	STORE_MAP         ''
5108	LOAD_NAME         'OneStringArgCommandProcessor'
5111	LOAD_NAME         'CHAT_COMMANDS'
5114	LOAD_ATTR         'GREETING'
5117	CALL_FUNCTION_1   ''
5120	LOAD_NAME         'CHAT_COMMANDS'
5123	LOAD_ATTR         'GREETING'
5126	STORE_MAP         ''
5127	LOAD_NAME         'OneStringArgCommandProcessor'
5130	LOAD_NAME         'CHAT_COMMANDS'
5133	LOAD_ATTR         'UNBAN'
5136	CALL_FUNCTION_1   ''
5139	LOAD_NAME         'CHAT_COMMANDS'
5142	LOAD_ATTR         'UNBAN'
5145	STORE_MAP         ''
5146	LOAD_NAME         'OneStringArgCommandProcessor'
5149	LOAD_NAME         'CHAT_COMMANDS'
5152	LOAD_ATTR         'ADDMODERATOR'
5155	CALL_FUNCTION_1   ''
5158	LOAD_NAME         'CHAT_COMMANDS'
5161	LOAD_ATTR         'ADDMODERATOR'
5164	STORE_MAP         ''
5165	LOAD_NAME         'OneStringArgCommandProcessor'
5168	LOAD_NAME         'CHAT_COMMANDS'
5171	LOAD_ATTR         'DELMODERATOR'
5174	CALL_FUNCTION_1   ''
5177	LOAD_NAME         'CHAT_COMMANDS'
5180	LOAD_ATTR         'DELMODERATOR'
5183	STORE_MAP         ''
5184	LOAD_NAME         'NoArgsCommandProcessor'
5187	LOAD_NAME         'CHAT_COMMANDS'
5190	LOAD_ATTR         'HELPME'
5193	CALL_FUNCTION_1   ''
5196	LOAD_NAME         'CHAT_COMMANDS'
5199	LOAD_ATTR         'HELPME'
5202	STORE_MAP         ''
5203	LOAD_NAME         'NoArgsCommandProcessor'
5206	LOAD_NAME         'CHAT_COMMANDS'
5209	LOAD_ATTR         'ATTACK'
5212	CALL_FUNCTION_1   ''
5215	LOAD_NAME         'CHAT_COMMANDS'
5218	LOAD_ATTR         'ATTACK'
5221	STORE_MAP         ''
5222	LOAD_NAME         'NoArgsCommandProcessor'
5225	LOAD_NAME         'CHAT_COMMANDS'
5228	LOAD_ATTR         'BACKTOBASE'
5231	CALL_FUNCTION_1   ''
5234	LOAD_NAME         'CHAT_COMMANDS'
5237	LOAD_ATTR         'BACKTOBASE'
5240	STORE_MAP         ''
5241	LOAD_NAME         'NoArgsCommandProcessor'
5244	LOAD_NAME         'CHAT_COMMANDS'
5247	LOAD_ATTR         'FOLLOWME'
5250	CALL_FUNCTION_1   ''
5253	LOAD_NAME         'CHAT_COMMANDS'
5256	LOAD_ATTR         'FOLLOWME'
5259	STORE_MAP         ''
5260	LOAD_NAME         'NoArgsCommandProcessor'
5263	LOAD_NAME         'CHAT_COMMANDS'
5266	LOAD_ATTR         'POSITIVE'
5269	CALL_FUNCTION_1   ''
5272	LOAD_NAME         'CHAT_COMMANDS'
5275	LOAD_ATTR         'POSITIVE'
5278	STORE_MAP         ''
5279	LOAD_NAME         'NoArgsCommandProcessor'
5282	LOAD_NAME         'CHAT_COMMANDS'
5285	LOAD_ATTR         'NEGATIVE'
5288	CALL_FUNCTION_1   ''
5291	LOAD_NAME         'CHAT_COMMANDS'
5294	LOAD_ATTR         'NEGATIVE'
5297	STORE_MAP         ''
5298	LOAD_NAME         'NoArgsCommandProcessor'
5301	LOAD_NAME         'CHAT_COMMANDS'
5304	LOAD_ATTR         'ATTENTIONTOCELL'
5307	CALL_FUNCTION_1   ''
5310	LOAD_NAME         'CHAT_COMMANDS'
5313	LOAD_ATTR         'ATTENTIONTOCELL'
5316	STORE_MAP         ''
5317	LOAD_NAME         'OneStringArgCommandProcessor'
5320	LOAD_NAME         'CHAT_COMMANDS'
5323	LOAD_ATTR         'ATTACKENEMY'
5326	CALL_FUNCTION_1   ''
5329	LOAD_NAME         'CHAT_COMMANDS'
5332	LOAD_ATTR         'ATTACKENEMY'
5335	STORE_MAP         ''
5336	LOAD_NAME         'UserBanCommandProcessor'
5339	CALL_FUNCTION_0   ''
5342	LOAD_NAME         'CHAT_COMMANDS'
5345	LOAD_ATTR         'USERBAN'
5348	STORE_MAP         ''
5349	LOAD_NAME         'UserUnbanCommandProcessor'
5352	CALL_FUNCTION_0   ''
5355	LOAD_NAME         'CHAT_COMMANDS'
5358	LOAD_ATTR         'USERUNBAN'
5361	STORE_MAP         ''
5362	STORE_NAME        '_g_chatCommandProcessors'
5365	LOAD_CONST        '<code_object initChatCooldownData>'
5368	MAKE_FUNCTION_0   ''
5371	STORE_NAME        'initChatCooldownData'
5374	LOAD_NAME         'constants'
5377	LOAD_ATTR         'IS_CLIENT'
5380	POP_JUMP_IF_TRUE  '5392'
5383	LOAD_NAME         'constants'
5386	LOAD_ATTR         'IS_BOT'
5389_0	COME_FROM         '5380'
5389	POP_JUMP_IF_FALSE '5404'
5392	LOAD_NAME         'initChatCooldownData'
5395	CALL_FUNCTION_0   ''
5398	STORE_NAME        'g_chatCooldownData'
5401	JUMP_FORWARD      '5404'
5404_0	COME_FROM         '5401'
5404	LOAD_NAME         'True'
5407	LOAD_CONST        '<code_object __isOperationInCooldown>'
5410	MAKE_FUNCTION_1   ''
5413	STORE_NAME        '__isOperationInCooldown'
5416	LOAD_NAME         'True'
5419	LOAD_CONST        '<code_object isOperationInCooldown>'
5422	MAKE_FUNCTION_1   ''
5425	STORE_NAME        'isOperationInCooldown'
5428	LOAD_CONST        '<code_object getOperationCooldownPeriod>'
5431	MAKE_FUNCTION_0   ''
5434	STORE_NAME        'getOperationCooldownPeriod'
5437	LOAD_CONST        'redfox'
5440	LOAD_CONST        'ars'
5443	LOAD_CONST        'snake'
5446	BUILD_LIST_3      ''
5449	STORE_NAME        '_g_chatadmins'
5452	LOAD_CONST        '<code_object isChatAdmin>'
5455	MAKE_FUNCTION_0   ''
5458	STORE_NAME        'isChatAdmin'
5461	LOAD_CONST        ''
5464	LOAD_CONST        ''
5467	LOAD_CONST        '<code_object __isCommandFromCategory>'
5470	MAKE_FUNCTION_2   ''
5473	STORE_NAME        '__isCommandFromCategory'
5476	LOAD_CONST        '<code_object isInviteCommand>'
5479	MAKE_FUNCTION_0   ''
5482	STORE_NAME        'isInviteCommand'
5485	LOAD_CONST        '<code_object isInviteCommandIdx>'
5488	MAKE_FUNCTION_0   ''
5491	STORE_NAME        'isInviteCommandIdx'
5494	LOAD_CONST        '<code_object isChannelChatCommand>'
5497	MAKE_FUNCTION_0   ''
5500	STORE_NAME        'isChannelChatCommand'
5503	LOAD_CONST        '<code_object isChannelChatCommandIdx>'
5506	MAKE_FUNCTION_0   ''
5509	STORE_NAME        'isChannelChatCommandIdx'
5512	LOAD_CONST        '<code_object isUserCommand>'
5515	MAKE_FUNCTION_0   ''
5518	STORE_NAME        'isUserCommand'
5521	LOAD_CONST        '<code_object isUserCommandIdx>'
5524	MAKE_FUNCTION_0   ''
5527	STORE_NAME        'isUserCommandIdx'
5530	LOAD_CONST        '<code_object isBattleChatCommand>'
5533	MAKE_FUNCTION_0   ''
5536	STORE_NAME        'isBattleChatCommand'
5539	LOAD_CONST        '<code_object isBattleChatCommandIdx>'
5542	MAKE_FUNCTION_0   ''
5545	STORE_NAME        'isBattleChatCommandIdx'
5548	LOAD_CONST        '<code_object isSkipBanCheckForChatCommand>'
5551	MAKE_FUNCTION_0   ''
5554	STORE_NAME        'isSkipBanCheckForChatCommand'
5557	LOAD_CONST        '<code_object isSkipBanCheckForCommandIdx>'
5560	MAKE_FUNCTION_0   ''
5563	STORE_NAME        'isSkipBanCheckForCommandIdx'
5566	LOAD_CONST        '<code_object isCommandMessage>'
5569	MAKE_FUNCTION_0   ''
5572	STORE_NAME        'isCommandMessage'
5575	LOAD_NAME         'True'
5578	LOAD_CONST        '<code_object parseCommandMessage>'
5581	MAKE_FUNCTION_1   ''
5584	STORE_NAME        'parseCommandMessage'
5587	LOAD_CONST        ''
5590	LOAD_CONST        ''
5593	LOAD_CONST        ''
5596	LOAD_CONST        ''
5599	LOAD_CONST        '<code_object verifyCommandData>'
5602	MAKE_FUNCTION_4   ''
5605	STORE_NAME        'verifyCommandData'
5608	LOAD_CONST        '<code_object isPermanentBan>'
5611	MAKE_FUNCTION_0   ''
5614	STORE_NAME        'isPermanentBan'
5617	LOAD_CONST        'ChatActionHandlers'
5620	LOAD_NAME         'object'
5623	BUILD_TUPLE_1     ''
5626	LOAD_CONST        '<code_object ChatActionHandlers>'
5629	MAKE_FUNCTION_0   ''
5632	CALL_FUNCTION_0   ''
5635	BUILD_CLASS       ''
5636	STORE_NAME        'ChatActionHandlers'
5639	LOAD_CONST        'ChatError'
5642	LOAD_CONST        ''
5645	LOAD_CONST        '<code_object ChatError>'
5648	MAKE_FUNCTION_0   ''
5651	CALL_FUNCTION_0   ''
5654	BUILD_CLASS       ''
5655	STORE_NAME        'ChatError'
5658	LOAD_CONST        'UserBannedError'
5661	LOAD_NAME         'ChatError'
5664	BUILD_TUPLE_1     ''
5667	LOAD_CONST        '<code_object UserBannedError>'
5670	MAKE_FUNCTION_0   ''
5673	CALL_FUNCTION_0   ''
5676	BUILD_CLASS       ''
5677	STORE_NAME        'UserBannedError'
5680	LOAD_CONST        'ChatBannedError'
5683	LOAD_NAME         'ChatError'
5686	BUILD_TUPLE_1     ''
5689	LOAD_CONST        '<code_object ChatBannedError>'
5692	MAKE_FUNCTION_0   ''
5695	CALL_FUNCTION_0   ''
5698	BUILD_CLASS       ''
5699	STORE_NAME        'ChatBannedError'
5702	LOAD_CONST        'ChatSQLError'
5705	LOAD_NAME         'ChatError'
5708	BUILD_TUPLE_1     ''
5711	LOAD_CONST        '<code_object ChatSQLError>'
5714	MAKE_FUNCTION_0   ''
5717	CALL_FUNCTION_0   ''
5720	BUILD_CLASS       ''
5721	STORE_NAME        'ChatSQLError'
5724	LOAD_CONST        'IncorrectCharacter'
5727	LOAD_NAME         'ChatError'
5730	BUILD_TUPLE_1     ''
5733	LOAD_CONST        '<code_object IncorrectCharacter>'
5736	MAKE_FUNCTION_0   ''
5739	CALL_FUNCTION_0   ''
5742	BUILD_CLASS       ''
5743	STORE_NAME        'IncorrectCharacter'
5746	LOAD_CONST        'AddFriendError'
5749	LOAD_NAME         'ChatError'
5752	BUILD_TUPLE_1     ''
5755	LOAD_CONST        '<code_object AddFriendError>'
5758	MAKE_FUNCTION_0   ''
5761	CALL_FUNCTION_0   ''
5764	BUILD_CLASS       ''
5765	STORE_NAME        'AddFriendError'
5768	LOAD_CONST        'AddIgnoredError'
5771	LOAD_NAME         'ChatError'
5774	BUILD_TUPLE_1     ''
5777	LOAD_CONST        '<code_object AddIgnoredError>'
5780	MAKE_FUNCTION_0   ''
5783	CALL_FUNCTION_0   ''
5786	BUILD_CLASS       ''
5787	STORE_NAME        'AddIgnoredError'
5790	LOAD_CONST        'SetMutedError'
5793	LOAD_NAME         'ChatError'
5796	BUILD_TUPLE_1     ''
5799	LOAD_CONST        '<code_object SetMutedError>'
5802	MAKE_FUNCTION_0   ''
5805	CALL_FUNCTION_0   ''
5808	BUILD_CLASS       ''
5809	STORE_NAME        'SetMutedError'
5812	LOAD_CONST        'UnsetMutedError'
5815	LOAD_NAME         'ChatError'
5818	BUILD_TUPLE_1     ''
5821	LOAD_CONST        '<code_object UnsetMutedError>'
5824	MAKE_FUNCTION_0   ''
5827	CALL_FUNCTION_0   ''
5830	BUILD_CLASS       ''
5831	STORE_NAME        'UnsetMutedError'
5834	LOAD_CONST        'UserIgnoredError'
5837	LOAD_NAME         'ChatError'
5840	BUILD_TUPLE_1     ''
5843	LOAD_CONST        '<code_object UserIgnoredError>'
5846	MAKE_FUNCTION_0   ''
5849	CALL_FUNCTION_0   ''
5852	BUILD_CLASS       ''
5853	STORE_NAME        'UserIgnoredError'
5856	LOAD_CONST        'CreatePrivateError'
5859	LOAD_NAME         'ChatError'
5862	BUILD_TUPLE_1     ''
5865	LOAD_CONST        '<code_object CreatePrivateError>'
5868	MAKE_FUNCTION_0   ''
5871	CALL_FUNCTION_0   ''
5874	BUILD_CLASS       ''
5875	STORE_NAME        'CreatePrivateError'
5878	LOAD_CONST        'ActiveChannelsLimitReached'
5881	LOAD_NAME         'ChatError'
5884	BUILD_TUPLE_1     ''
5887	LOAD_CONST        '<code_object ActiveChannelsLimitReached>'
5890	MAKE_FUNCTION_0   ''
5893	CALL_FUNCTION_0   ''
5896	BUILD_CLASS       ''
5897	STORE_NAME        'ActiveChannelsLimitReached'
5900	LOAD_CONST        'UsersRosterLimitReached'
5903	LOAD_NAME         'ChatError'
5906	BUILD_TUPLE_1     ''
5909	LOAD_CONST        '<code_object UsersRosterLimitReached>'
5912	MAKE_FUNCTION_0   ''
5915	CALL_FUNCTION_0   ''
5918	BUILD_CLASS       ''
5919	STORE_NAME        'UsersRosterLimitReached'
5922	LOAD_CONST        'ChatCommandError'
5925	LOAD_NAME         'ChatError'
5928	BUILD_TUPLE_1     ''
5931	LOAD_CONST        '<code_object ChatCommandError>'
5934	MAKE_FUNCTION_0   ''
5937	CALL_FUNCTION_0   ''
5940	BUILD_CLASS       ''
5941	STORE_NAME        'ChatCommandError'
5944	LOAD_CONST        'InviteCommandError'
5947	LOAD_NAME         'ChatError'
5950	BUILD_TUPLE_1     ''
5953	LOAD_CONST        '<code_object InviteCommandError>'
5956	MAKE_FUNCTION_0   ''
5959	CALL_FUNCTION_0   ''
5962	BUILD_CLASS       ''
5963	STORE_NAME        'InviteCommandError'
5966	LOAD_CONST        'InviteCreateError'
5969	LOAD_NAME         'InviteCommandError'
5972	BUILD_TUPLE_1     ''
5975	LOAD_CONST        '<code_object InviteCreateError>'
5978	MAKE_FUNCTION_0   ''
5981	CALL_FUNCTION_0   ''
5984	BUILD_CLASS       ''
5985	STORE_NAME        'InviteCreateError'
5988	LOAD_CONST        'InviteCreationNotAllowed'
5991	LOAD_NAME         'InviteCreateError'
5994	BUILD_TUPLE_1     ''
5997	LOAD_CONST        '<code_object InviteCreationNotAllowed>'
6000	MAKE_FUNCTION_0   ''
6003	CALL_FUNCTION_0   ''
6006	BUILD_CLASS       ''
6007	STORE_NAME        'InviteCreationNotAllowed'
6010	LOAD_CONST        'ChatCommandInCooldown'
6013	LOAD_NAME         'ChatCommandError'
6016	BUILD_TUPLE_1     ''
6019	LOAD_CONST        '<code_object ChatCommandInCooldown>'
6022	MAKE_FUNCTION_0   ''
6025	CALL_FUNCTION_0   ''
6028	BUILD_CLASS       ''
6029	STORE_NAME        'ChatCommandInCooldown'
6032	LOAD_CONST        'ChatCommandNotAllowedError'
6035	LOAD_NAME         'ChatCommandError'
6038	BUILD_TUPLE_1     ''
6041	LOAD_CONST        '<code_object ChatCommandNotAllowedError>'
6044	MAKE_FUNCTION_0   ''
6047	CALL_FUNCTION_0   ''
6050	BUILD_CLASS       ''
6051	STORE_NAME        'ChatCommandNotAllowedError'
6054	LOAD_CONST        'MemberAlreadyBanned'
6057	LOAD_NAME         'ChatCommandError'
6060	BUILD_TUPLE_1     ''
6063	LOAD_CONST        '<code_object MemberAlreadyBanned>'
6066	MAKE_FUNCTION_0   ''
6069	CALL_FUNCTION_0   ''
6072	BUILD_CLASS       ''
6073	STORE_NAME        'MemberAlreadyBanned'
6076	LOAD_CONST        'MemberAlreadyModerator'
6079	LOAD_NAME         'ChatCommandError'
6082	BUILD_TUPLE_1     ''
6085	LOAD_CONST        '<code_object MemberAlreadyModerator>'
6088	MAKE_FUNCTION_0   ''
6091	CALL_FUNCTION_0   ''
6094	BUILD_CLASS       ''
6095	STORE_NAME        'MemberAlreadyModerator'
6098	LOAD_CONST        'MemberNotModerator'
6101	LOAD_NAME         'ChatCommandError'
6104	BUILD_TUPLE_1     ''
6107	LOAD_CONST        '<code_object MemberNotModerator>'
6110	MAKE_FUNCTION_0   ''
6113	CALL_FUNCTION_0   ''
6116	BUILD_CLASS       ''
6117	STORE_NAME        'MemberNotModerator'
6120	LOAD_CONST        'IncorrectCommandArgumentError'
6123	LOAD_NAME         'ChatCommandError'
6126	BUILD_TUPLE_1     ''
6129	LOAD_CONST        '<code_object IncorrectCommandArgumentError>'
6132	MAKE_FUNCTION_0   ''
6135	CALL_FUNCTION_0   ''
6138	BUILD_CLASS       ''
6139	STORE_NAME        'IncorrectCommandArgumentError'
6142	LOAD_CONST        'ChatException'
6145	LOAD_NAME         'ChatError'
6148	LOAD_NAME         'Exception'
6151	BUILD_TUPLE_2     ''
6154	LOAD_CONST        '<code_object ChatException>'
6157	MAKE_FUNCTION_0   ''
6160	CALL_FUNCTION_0   ''
6163	BUILD_CLASS       ''
6164	STORE_NAME        'ChatException'
6167	LOAD_CONST        'ChannelNotExists'
6170	LOAD_NAME         'ChatException'
6173	BUILD_TUPLE_1     ''
6176	LOAD_CONST        '<code_object ChannelNotExists>'
6179	MAKE_FUNCTION_0   ''
6182	CALL_FUNCTION_0   ''
6185	BUILD_CLASS       ''
6186	STORE_NAME        'ChannelNotExists'
6189	LOAD_CONST        'UserNotExists'
6192	LOAD_NAME         'ChatException'
6195	BUILD_TUPLE_1     ''
6198	LOAD_CONST        '<code_object UserNotExists>'
6201	MAKE_FUNCTION_0   ''
6204	CALL_FUNCTION_0   ''
6207	BUILD_CLASS       ''
6208	STORE_NAME        'UserNotExists'
6211	LOAD_NAME         'Enumeration'
6214	LOAD_CONST        'systemMessageType'
6217	LOAD_CONST        'serverReboot'
6220	LOAD_CONST        'serverRebootCancelled'
6223	LOAD_CONST        'battleResults'
6226	LOAD_CONST        'achievements'
6229	LOAD_CONST        'goldReceived'
6232	LOAD_CONST        'accountTypeChanged'
6235	LOAD_CONST        'adminTextMessage'
6238	LOAD_CONST        'accountNameChanged'
6241	LOAD_CONST        'invoiceReceived'
6244	LOAD_CONST        'giftReceived'
6247	LOAD_CONST        'autoMaintenance'
6250	LOAD_CONST        'tradeOfferReceived'
6253	LOAD_CONST        'tradeOfferDeclined'
6256	LOAD_CONST        'waresSold'
6259	LOAD_CONST        'waresBought'
6262	LOAD_CONST        'premiumBought'
6265	LOAD_CONST        'premiumExtended'
6268	LOAD_CONST        'premiumExpired'
6271	LOAD_CONST        'prbArenaFinish'
6274	LOAD_CONST        'prbKick'
6277	LOAD_CONST        'prbDestruction'
6280	LOAD_CONST        'vehicleCamouflageTimedOut'
6283	LOAD_CONST        'vehTypeLockExpired'
6286	LOAD_CONST        'accountDeleted'
6289	LOAD_CONST        'serverDowntimeCompensation'
6292	LOAD_CONST        'vehiclePlayerEmblemTimedOut'
6295	LOAD_CONST        'vehiclePlayerInscriptionTimedOut'
6298	LOAD_CONST        'achievementReceived'
6301	LOAD_CONST        'converter'
6304	LOAD_CONST        'tokenQuests'
6307	LOAD_CONST        'notificationsCenter'
6310	LOAD_CONST        'historicalCostsReserved'
6313	LOAD_CONST        'clanEvent'
6316	LOAD_CONST        'fortEvent'
6319	LOAD_CONST        'fortBattleInvite'
6322	LOAD_CONST        'fortBattleEnd'
6325	LOAD_CONST        'fortBattleRoundEnd'
6328	LOAD_CONST        'refSystemQuests'
6331	LOAD_CONST        'refSystemReferralBoughtVehicle'
6334	LOAD_CONST        'refSystemReferralContributedXP'
6337	LOAD_CONST        'vehicleRented'
6340	LOAD_CONST        'rentalsExpired'
6343	LOAD_CONST        'rentCompensation'
6346	LOAD_CONST        'potapovQuestBonus'
6349	BUILD_LIST_44     ''
6352	CALL_FUNCTION_2   ''
6355	STORE_NAME        'SYS_MESSAGE_TYPE'
6358	LOAD_NAME         'Enumeration'
6361	LOAD_CONST        'systemMessageImportance'
6364	LOAD_CONST        'normal'
6367	LOAD_CONST        'high'
6370	BUILD_LIST_2      ''
6373	CALL_FUNCTION_2   ''
6376	STORE_NAME        'SYS_MESSAGE_IMPORTANCE'
6379	LOAD_CONST        1
6382	STORE_NAME        'SM_REQUEST_PERSONAL_MESSAGES_FLAG'
6385	LOAD_CONST        2
6388	STORE_NAME        'SM_REQUEST_SYSTEM_MESSAGES_FLAG'
6391	LOAD_CONST        4
6394	STORE_NAME        'SM_REQUEST_INTERNAL_SYS_MESSAGES_FLAG'
6397	LOAD_CONST        '<code_object isMembersListSupported>'
6400	MAKE_FUNCTION_0   ''
6403	STORE_NAME        'isMembersListSupported'
6406	LOAD_CONST        '<code_object isMembersListSupportedByFlags>'
6409	MAKE_FUNCTION_0   ''
6412	STORE_NAME        'isMembersListSupportedByFlags'
6415	LOAD_CONST        '<code_object getMembersListMode>'
6418	MAKE_FUNCTION_0   ''
6421	STORE_NAME        'getMembersListMode'
6424	LOAD_CONST        '<code_object setMembersListMode>'
6427	MAKE_FUNCTION_0   ''
6430	STORE_NAME        'setMembersListMode'
6433	LOAD_CONST        1
6436	STORE_NAME        'USERS_ROSTER_FRIEND'
6439	LOAD_CONST        2
6442	STORE_NAME        'USERS_ROSTER_IGNORED'
6445	LOAD_CONST        4
6448	STORE_NAME        'USERS_ROSTER_VOICE_MUTED'
6451	LOAD_CONST        '<code_object isFromFriendRoster>'
6454	MAKE_FUNCTION_0   ''
6457	STORE_NAME        'isFromFriendRoster'
6460	LOAD_CONST        '<code_object isFromIgnoreRoster>'
6463	MAKE_FUNCTION_0   ''
6466	STORE_NAME        'isFromIgnoreRoster'
6469	LOAD_CONST        '<code_object isVoiceMuted>'
6472	MAKE_FUNCTION_0   ''
6475	STORE_NAME        'isVoiceMuted'
6478	LOAD_CONST        '<code_object _checkRosterAccessBitmask>'
6481	MAKE_FUNCTION_0   ''
6484	STORE_NAME        '_checkRosterAccessBitmask'
6487	LOAD_CONST        'MESSAGE_FILTER_TYPE'
6490	LOAD_NAME         'object'
6493	BUILD_TUPLE_1     ''
6496	LOAD_CONST        '<code_object MESSAGE_FILTER_TYPE>'
6499	MAKE_FUNCTION_0   ''
6502	CALL_FUNCTION_0   ''
6505	BUILD_CLASS       ''
6506	STORE_NAME        'MESSAGE_FILTER_TYPE'
6509	LOAD_CONST        '<code_object compressSysMessage>'
6512	MAKE_FUNCTION_0   ''
6515	STORE_NAME        'compressSysMessage'
6518	LOAD_CONST        '<code_object decompressSysMessage>'
6521	MAKE_FUNCTION_0   ''
6524	STORE_NAME        'decompressSysMessage'

Syntax error at or near `STORE_NAME' token at offset 4469
# decompiled 0 files: 0 okay, 1 failed, 0 verify failed
# 2015.01.14 22:42:56 CET
