# 2015.01.14 22:42:58 CET
--- This code section failed: ---
0	LOAD_CONST        -1
3	LOAD_CONST        ''
6	IMPORT_NAME       're'
9	STORE_NAME        're'
12	LOAD_CONST        -1
15	LOAD_CONST        ''
18	IMPORT_NAME       'unicodedata'
21	STORE_NAME        'unicodedata'
24	LOAD_CONST        -1
27	LOAD_CONST        ('LOG_CURRENT_EXCEPTION',)
30	IMPORT_NAME       'debug_utils'
33	IMPORT_FROM       'LOG_CURRENT_EXCEPTION'
36	STORE_NAME        'LOG_CURRENT_EXCEPTION'
39	POP_TOP           ''
40	LOAD_CONST        -1
43	LOAD_CONST        ('CREDENTIALS_RESTRICTION', 'CREDENTIALS_RESTRICTION_SET')
46	IMPORT_NAME       'constants'
49	IMPORT_FROM       'CREDENTIALS_RESTRICTION'
52	STORE_NAME        'CREDENTIALS_RESTRICTION'
55	IMPORT_FROM       'CREDENTIALS_RESTRICTION_SET'
58	STORE_NAME        'CREDENTIALS_RESTRICTION_SET'
61	POP_TOP           ''
62	LOAD_NAME         'CREDENTIALS_RESTRICTION_SET'
65	LOAD_NAME         'CREDENTIALS_RESTRICTION'
68	LOAD_ATTR         'BASIC'
71	COMPARE_OP        '=='
74	POP_JUMP_IF_FALSE '218'
77	LOAD_NAME         're'
80	LOAD_ATTR         'compile'
83	LOAD_CONST        '^[a-zA-Z0-9_]+$'
86	CALL_FUNCTION_1   ''
89	STORE_NAME        '_ACCOUNT_NAME_RE'
92	LOAD_CONST        2
95	STORE_NAME        '_ACCOUNT_NAME_MIN_LENGTH'
98	LOAD_CONST        24
101	STORE_NAME        '_ACCOUNT_NAME_MAX_LENGTH'
104	LOAD_CONST        3
107	STORE_NAME        '_ACCOUNT_NAME_MIN_LENGTH_REG'
110	LOAD_NAME         're'
113	LOAD_ATTR         'compile'
116	LOAD_CONST        '^[a-z0-9_-]+(\\.[a-z0-9_-]+)*@[a-z0-9-]+(\\.[a-z0-9-]+)*\\.([a-z]{2,4})$'
119	CALL_FUNCTION_1   ''
122	STORE_NAME        '_LOGIN_NAME_RE'
125	LOAD_CONST        1
128	STORE_NAME        '_LOGIN_NAME_MIN_LENGTH'
131	LOAD_CONST        255
134	STORE_NAME        '_LOGIN_NAME_MAX_LENGTH'
137	LOAD_NAME         're'
140	LOAD_ATTR         'compile'
143	LOAD_CONST        '^[a-zA-Z0-9_]+$'
146	CALL_FUNCTION_1   ''
149	STORE_NAME        '_PASSWORD_RE'
152	LOAD_CONST        6
155	STORE_NAME        '_PASSWORD_MIN_LENGTH'
158	LOAD_CONST        100
161	STORE_NAME        '_PASSWORD_MAX_LENGTH'
164	LOAD_NAME         're'
167	LOAD_ATTR         'compile'
170	LOAD_CONST        '^[A-Z0-9_\\-]+$'
173	CALL_FUNCTION_1   ''
176	STORE_NAME        '_CLAN_ABBREV_RE'
179	LOAD_CONST        70
182	STORE_NAME        '_CLAN_NAME_MAX_LENGTH'
185	LOAD_CONST        5
188	STORE_NAME        '_CLAN_ABBREV_MAX_LENGTH'
191	LOAD_NAME         'True'
194	STORE_NAME        '_UPPERCASE_CLAN_ABBREV'
197	LOAD_NAME         'True'
200	STORE_NAME        '_REQUIRE_NORMALIZED_CLAN_ABBREV'
203	LOAD_CONST        1000
206	STORE_NAME        'CLAN_DESCR_MAX_LENGTH'
209	LOAD_CONST        100
212	STORE_NAME        'CLAN_MOTTO_MAX_LENGTH'
215	JUMP_FORWARD      '631'
218	LOAD_NAME         'CREDENTIALS_RESTRICTION_SET'
221	LOAD_NAME         'CREDENTIALS_RESTRICTION'
224	LOAD_ATTR         'CHINESE'
227	COMPARE_OP        '=='
230	POP_JUMP_IF_FALSE '457'
233	LOAD_NAME         'range'
236	LOAD_CONST        32
239	CALL_FUNCTION_1   ''
242	LOAD_CONST        34
245	LOAD_CONST        38
248	LOAD_CONST        39
251	LOAD_CONST        47
254	LOAD_CONST        58
257	LOAD_CONST        60
260	LOAD_CONST        62
263	LOAD_CONST        64
266	LOAD_CONST        127
269	BUILD_LIST_9      ''
272	BINARY_ADD        ''
273	STORE_NAME        '_ACCOUNT_NAME_EXCLUDED_SYMBOLS'
276	LOAD_NAME         're'
279	LOAD_ATTR         'compile'
282	LOAD_CONST        u'(?u)^[^'
285	LOAD_CONST        ''
288	LOAD_ATTR         'join'
291	LOAD_NAME         'map'
294	LOAD_LAMBDA       '<code_object <lambda>>'
297	MAKE_FUNCTION_0   ''
300	LOAD_NAME         '_ACCOUNT_NAME_EXCLUDED_SYMBOLS'
303	CALL_FUNCTION_2   ''
306	CALL_FUNCTION_1   ''
309	BINARY_ADD        ''
310	LOAD_NAME         'unichr'
313	LOAD_CONST        65535
316	CALL_FUNCTION_1   ''
319	BINARY_ADD        ''
320	LOAD_NAME         'unichr'
323	LOAD_CONST        65534
326	CALL_FUNCTION_1   ''
329	BINARY_ADD        ''
330	LOAD_CONST        u']+$'
333	BINARY_ADD        ''
334	CALL_FUNCTION_1   ''
337	STORE_NAME        '_ACCOUNT_NAME_RE'
340	LOAD_CONST        2
343	STORE_NAME        '_ACCOUNT_NAME_MIN_LENGTH'
346	LOAD_CONST        24
349	STORE_NAME        '_ACCOUNT_NAME_MAX_LENGTH'
352	LOAD_NAME         '_ACCOUNT_NAME_MIN_LENGTH'
355	STORE_NAME        '_ACCOUNT_NAME_MIN_LENGTH_REG'
358	LOAD_NAME         're'
361	LOAD_ATTR         'compile'
364	LOAD_CONST        '^[_a-z0-9-+@.]+$'
367	CALL_FUNCTION_1   ''
370	STORE_NAME        '_LOGIN_NAME_RE'
373	LOAD_CONST        4
376	STORE_NAME        '_LOGIN_NAME_MIN_LENGTH'
379	LOAD_CONST        50
382	STORE_NAME        '_LOGIN_NAME_MAX_LENGTH'
385	LOAD_NAME         're'
388	LOAD_ATTR         'compile'
391	LOAD_CONST        '^[!-~]+$'
394	CALL_FUNCTION_1   ''
397	STORE_NAME        '_PASSWORD_RE'
400	LOAD_CONST        6
403	STORE_NAME        '_PASSWORD_MIN_LENGTH'
406	LOAD_CONST        32
409	STORE_NAME        '_PASSWORD_MAX_LENGTH'
412	LOAD_NAME         '_ACCOUNT_NAME_RE'
415	STORE_NAME        '_CLAN_ABBREV_RE'
418	LOAD_CONST        70
421	STORE_NAME        '_CLAN_NAME_MAX_LENGTH'
424	LOAD_CONST        5
427	STORE_NAME        '_CLAN_ABBREV_MAX_LENGTH'
430	LOAD_NAME         'False'
433	STORE_NAME        '_UPPERCASE_CLAN_ABBREV'
436	LOAD_NAME         'False'
439	STORE_NAME        '_REQUIRE_NORMALIZED_CLAN_ABBREV'
442	LOAD_CONST        1000
445	STORE_NAME        'CLAN_DESCR_MAX_LENGTH'
448	LOAD_CONST        100
451	STORE_NAME        'CLAN_MOTTO_MAX_LENGTH'
454	JUMP_FORWARD      '631'
457	LOAD_NAME         'CREDENTIALS_RESTRICTION_SET'
460	LOAD_NAME         'CREDENTIALS_RESTRICTION'
463	LOAD_ATTR         'VIETNAM'
466	COMPARE_OP        '=='
469	POP_JUMP_IF_FALSE '613'
472	LOAD_NAME         're'
475	LOAD_ATTR         'compile'
478	LOAD_CONST        '^[a-zA-Z0-9_]+$'
481	CALL_FUNCTION_1   ''
484	STORE_NAME        '_ACCOUNT_NAME_RE'
487	LOAD_CONST        2
490	STORE_NAME        '_ACCOUNT_NAME_MIN_LENGTH'
493	LOAD_CONST        24
496	STORE_NAME        '_ACCOUNT_NAME_MAX_LENGTH'
499	LOAD_CONST        3
502	STORE_NAME        '_ACCOUNT_NAME_MIN_LENGTH_REG'
505	LOAD_NAME         're'
508	LOAD_ATTR         'compile'
511	LOAD_CONST        '^[a-zA-Z0-9_][a-zA-Z0-9._]+$'
514	CALL_FUNCTION_1   ''
517	STORE_NAME        '_LOGIN_NAME_RE'
520	LOAD_CONST        3
523	STORE_NAME        '_LOGIN_NAME_MIN_LENGTH'
526	LOAD_CONST        24
529	STORE_NAME        '_LOGIN_NAME_MAX_LENGTH'
532	LOAD_NAME         're'
535	LOAD_ATTR         'compile'
538	LOAD_CONST        '^[a-zA-Z0-9+!@#$%^&*()?.,_=";:><{}\\[\\]\']+$'
541	CALL_FUNCTION_1   ''
544	STORE_NAME        '_PASSWORD_RE'
547	LOAD_CONST        4
550	STORE_NAME        '_PASSWORD_MIN_LENGTH'
553	LOAD_CONST        32
556	STORE_NAME        '_PASSWORD_MAX_LENGTH'
559	LOAD_NAME         're'
562	LOAD_ATTR         'compile'
565	LOAD_CONST        '^[A-Z0-9_\\-]+$'
568	CALL_FUNCTION_1   ''
571	STORE_NAME        '_CLAN_ABBREV_RE'
574	LOAD_CONST        70
577	STORE_NAME        '_CLAN_NAME_MAX_LENGTH'
580	LOAD_CONST        5
583	STORE_NAME        '_CLAN_ABBREV_MAX_LENGTH'
586	LOAD_NAME         'True'
589	STORE_NAME        '_UPPERCASE_CLAN_ABBREV'
592	LOAD_NAME         'True'
595	STORE_NAME        '_REQUIRE_NORMALIZED_CLAN_ABBREV'
598	LOAD_CONST        1000
601	STORE_NAME        'CLAN_DESCR_MAX_LENGTH'
604	LOAD_CONST        100
607	STORE_NAME        'CLAN_MOTTO_MAX_LENGTH'
610	JUMP_FORWARD      '631'
613	LOAD_NAME         'False'
616	POP_JUMP_IF_TRUE  '631'
619	LOAD_ASSERT       'AssertionError'
622	LOAD_CONST        'Unknown credential restrictions set'
625	CALL_FUNCTION_1   ''
628	RAISE_VARARGS     ''
631_0	COME_FROM         '215'
631_1	COME_FROM         '454'
631_2	COME_FROM         '610'
631	LOAD_CONST        '<code_object getClanAbbrevMaxLength>'
634	MAKE_FUNCTION_0   ''
637	STORE_NAME        'getClanAbbrevMaxLength'
640	LOAD_NAME         'CLAN_DESCR_MAX_LENGTH'
643	LOAD_CONST        4
646	BINARY_MULTIPLY   ''
647	STORE_NAME        'CLAN_DESCR_MAX_BYTES'
650	LOAD_NAME         'CLAN_MOTTO_MAX_LENGTH'
653	LOAD_CONST        4
656	BINARY_MULTIPLY   ''
657	STORE_NAME        'CLAN_MOTTO_MAX_BYTES'
660	LOAD_CONST        'NFKC'
663	LOAD_CONST        '<code_object unicode_from_utf8>'
666	MAKE_FUNCTION_1   ''
669	STORE_NAME        'unicode_from_utf8'
672	LOAD_CONST        'NFKC'
675	LOAD_NAME         'True'
678	LOAD_CONST        '<code_object utf8_accepted>'
681	MAKE_FUNCTION_2   ''
684	STORE_NAME        'utf8_accepted'
687	LOAD_CONST        'NFKC'
690	LOAD_CONST        '<code_object normalized_unicode_trim>'
693	MAKE_FUNCTION_1   ''
696	STORE_NAME        'normalized_unicode_trim'
699	LOAD_CONST        'NFKC'
702	LOAD_CONST        '<code_object normalized_unicode_trim_and_lowercase>'
705	MAKE_FUNCTION_1   ''
708	STORE_NAME        'normalized_unicode_trim_and_lowercase'
711	LOAD_NAME         '_ACCOUNT_NAME_MIN_LENGTH'
714	LOAD_CONST        '<code_object isAccountNameValid>'
717	MAKE_FUNCTION_1   ''
720	STORE_NAME        'isAccountNameValid'
723	LOAD_CONST        '<code_object normalizedAccountName>'
726	MAKE_FUNCTION_0   ''
729	STORE_NAME        'normalizedAccountName'
732	LOAD_CONST        '<code_object isPasswordValid>'
735	MAKE_FUNCTION_0   ''
738	STORE_NAME        'isPasswordValid'
741	LOAD_CONST        '<code_object isAccountLoginValid>'
744	MAKE_FUNCTION_0   ''
747	STORE_NAME        'isAccountLoginValid'
750	LOAD_CONST        '<code_object normalizedAccountLogin>'
753	MAKE_FUNCTION_0   ''
756	STORE_NAME        'normalizedAccountLogin'
759	LOAD_CONST        '<code_object isClanNameValid>'
762	MAKE_FUNCTION_0   ''
765	STORE_NAME        'isClanNameValid'
768	LOAD_CONST        '<code_object normalizedClanName>'
771	MAKE_FUNCTION_0   ''
774	STORE_NAME        'normalizedClanName'
777	LOAD_CONST        '<code_object isClanAbbrevValid>'
780	MAKE_FUNCTION_0   ''
783	STORE_NAME        'isClanAbbrevValid'
786	LOAD_CONST        '<code_object normalizedClanAbbrev>'
789	MAKE_FUNCTION_0   ''
792	STORE_NAME        'normalizedClanAbbrev'
795	LOAD_CONST        '<code_object isChannelNameValid>'
798	MAKE_FUNCTION_0   ''
801	STORE_NAME        'isChannelNameValid'
804	LOAD_CONST        '\\0'
807	LOAD_CONST        '<code_object escapeSQL>'
810	MAKE_FUNCTION_1   ''
813	STORE_NAME        'escapeSQL'
816	LOAD_CONST        '<code_object normalize_utf8>'
819	MAKE_FUNCTION_0   ''
822	STORE_NAME        'normalize_utf8'
825	LOAD_CONST        '<code_object truncate_utf8>'
828	MAKE_FUNCTION_0   ''
831	STORE_NAME        'truncate_utf8'
834	LOAD_CONST        '<code_object _is_utf8_one_byte>'
837	MAKE_FUNCTION_0   ''
840	STORE_NAME        '_is_utf8_one_byte'
843	LOAD_CONST        '<code_object _is_utf8_first_byte>'
846	MAKE_FUNCTION_0   ''
849	STORE_NAME        '_is_utf8_first_byte'
852	LOAD_CONST        '<code_object _decode_utf8_len_byte>'
855	MAKE_FUNCTION_0   ''
858	STORE_NAME        '_decode_utf8_len_byte'

Syntax error at or near `COME_FROM' token at offset 631_0
# decompiled 0 files: 0 okay, 1 failed, 0 verify failed
# 2015.01.14 22:42:58 CET
